Workbook

Sheet Commission Summary
A1: Doral Office Binder Book - June 2026 Commission Statement
A2: Universal Insurance Brokers | Producer: Jorge | Statement period 06/01/2026 - 06/30/2026
A3: Commission taken from each carrier commission statement at the rate that carrier shows, matched by policy number. United Auto is booked at 10% as collected.
A5: Producer | B5: Customer Name | C5: Binder Status | D5: New / Renewal | E5: Line of Business | F5: Carrier | G5: Policy Number | H5: Eff. Date | I5: Term (mo) | J5: Binder Premium | K5: Carrier Statement Used | L5: # Txns | M5: Carrier Comm Rate | N5: Commissionable Premium | O5: Commission Earned | P5: Effective Rate | Q5: Notes | R5: key
A6: NEW BUSINESS
A7: Jorge | B7: MARLENE CASTILLO | C7: Active | D7: New Business | E7: Personal Auto | F7: Infinity | G7: 10268755201 | H7: 6/1/2026 | I7: 6 | J7: 1183 | K7: Kemper Auto Monthly Producer Stmt 06/2026 | L7: =COUNTIF('Transaction Detail'!$A$2:$A$385,$R7) -> 1 | M7: 0.1 | N7: =SUMIF('Transaction Detail'!$A$2:$A$385,$R7,'Transaction Detail'!$N$2:$N$385) -> 1183 | O7: =SUMIF('Transaction Detail'!$A$2:$A$385,$R7,'Transaction Detail'!$O$2:$O$385) -> 118.3 | P7: =IF(N7=0,"",O7/N7) -> 0.1 | R7: Infinity|10268755201
A8: Jorge | B8: LIONEL JOHNSON | C8: Active | D8: New Business | E8: Personal Auto | F8: Infinity | G8: 10268783901 | H8: 6/5/2026 | I8: 6 | J8: 944 | K8: Kemper Auto Monthly Producer Stmt 06/2026 | L8: =COUNTIF('Transaction Detail'!$A$2:$A$385,$R8) -> 1 | M8: 0.1 | N8: =SUMIF('Transaction Detail'!$A$2:$A$385,$R8,'Transaction Detail'!$N$2:$N$385) -> 934 | O8: =SUMIF('Transaction Detail'!$A$2:$A$385,$R8,'Transaction Detail'!$O$2:$O$385) -> 93.4 | P8: =IF(N8=0,"",O8/N8) -> 0.1 | R8: Infinity|10268783901
A9: Jorge | B9: LUIS A. ORTIZ | C9: Active | D9: New Business | E9: Personal Auto | F9: United Auto | G9: UAO 692181 | H9: 6/2/2026 | I9: 12 | J9: 1103.35 | K9: United Insurance Group Direct Billing Stmt 06/2026 | L9: =COUNTIF('Transaction Detail'!$A$2:$A$385,$R9) -> 2 | M9: 0.1 | N9: =SUMIF('Transaction Detail'!$A$2:$A$385,$R9,'Transaction Detail'!$N$2:$N$385) -> 163.6 | O9: =SUMIF('Transaction Detail'!$A$2:$A$385,$R9,'Transaction Detail'!$O$2:$O$385) -> 16.36 | P9: =IF(N9=0,"",O9/N9) -> 0.1 | Q9: United bills this policy direct and pays AS COLLECTED, so June earns commission only on the premium United collected in June - more follows in later months. | Booked at 10% as collected. United also paid a separate 3% promotional incentive of $4.90 on this policy - it is shown on the Transaction Detail tab but is deliberately EXCLUDED from this total. | | R9: United Auto|UAO692181
A10: Jorge | B10: GREGORIO QUIROZ | C10: Active | D10: New Business | E10: Personal Auto | F10: Progressive | G10: 875244202 | H10: 6/6/2026 | I10: 6 | J10: 1175 | K10: Progressive Detailed Statement 06/2026 | L10: =COUNTIF('Transaction Detail'!$A$2:$A$385,$R10) -> 1 | M10: 0.12 | N10: =SUMIF('Transaction Detail'!$A$2:$A$385,$R10,'Transaction Detail'!$N$2:$N$385) -> 1175 | O10: =SUMIF('Transaction Detail'!$A$2:$A$385,$R10,'Transaction Detail'!$O$2:$O$385) -> 141 | P10: =IF(N10=0,"",O10/N10) -> 0.12 | R10: Progressive|875244202
A11: Jorge | B11: JULIO RAMIREZ | C11: Active | D11: New Business | E11: Personal Auto | F11: Progressive | G11: 875310026 | H11: 6/8/2026 | I11: 6 | J11: 1935 | K11: Progressive Detailed Statement 06/2026 | L11: =COUNTIF('Transaction Detail'!$A$2:$A$385,$R11) -> 3 | M11: 0.14 | N11: =SUMIF('Transaction Detail'!$A$2:$A$385,$R11,'Transaction Detail'!$N$2:$N$385) -> 1413.29 | O11: =SUMIF('Transaction Detail'!$A$2:$A$385,$R11,'Transaction Detail'!$O$2:$O$385) -> 197.86 | P11: =IF(N11=0,"",O11/N11) -> 0.13999958 | Q11: Credit Endorsement -277.00 @ 14%; New Business 1,935.00 @ 14%; Credit Endorsement -244.71 @ 14% | R11: Progressive|875310026
A12: Jorge | B12: JAMIE JONES | C12: Active | D12: New Business | E12: Personal Auto | F12: Progressive | G12: 875520372 | H12: 6/12/2026 | I12: 6 | J12: 4319 | K12: Progressive Detailed Statement 06/2026 | L12: =COUNTIF('Transaction Detail'!$A$2:$A$385,$R12) -> 1 | M12: 0.1 | N12: =SUMIF('Transaction Detail'!$A$2:$A$385,$R12,'Transaction Detail'!$N$2:$N$385) -> 4319 | O12: =SUMIF('Transaction Detail'!$A$2:$A$385,$R12,'Transaction Detail'!$O$2:$O$385) -> 431.9 | P12: =IF(N12=0,"",O12/N12) -> 0.1 | R12: Progressive|875520372
A13: Jorge | B13: YUDMILA CADENAS | C13: Active | D13: New Business | E13: Personal Auto | F13: Progressive | G13: 875557253 | H13: 6/13/2026 | I13: 6 | J13: 1071 | K13: Progressive Detailed Statement 06/2026 | L13: =COUNTIF('Transaction Detail'!$A$2:$A$385,$R13) -> 1 | M13: 0.1 | N13: =SUMIF('Transaction Detail'!$A$2:$A$385,$R13,'Transaction Detail'!$N$2:$N$385) -> 1071 | O13: =SUMIF('Transaction Detail'!$A$2:$A$385,$R13,'Transaction Detail'!$O$2:$O$385) -> 107.1 | P13: =IF(N13=0,"",O13/N13) -> 0.1 | R13: Progressive|875557253
A14: Jorge | B14: JEAN H. GUSTAVE | C14: Active | D14: New Business | E14: Personal Auto | F14: United Auto | G14: UAO 694805 | H14: 6/13/2026 | I14: 12 | J14: 2840.35 | K14: United Insurance Group Direct Billing Stmt 06/2026 | L14: =COUNTIF('Transaction Detail'!$A$2:$A$385,$R14) -> 2 | M14: 0.1 | N14: =SUMIF('Transaction Detail'!$A$2:$A$385,$R14,'Transaction Detail'!$N$2:$N$385) -> 2797 | O14: =SUMIF('Transaction Detail'!$A$2:$A$385,$R14,'Transaction Detail'!$O$2:$O$385) -> 279.7 | P14: =IF(N14=0,"",O14/N14) -> 0.1 | Q14: Booked at 10% as collected. United also paid a separate 3% promotional incentive of $83.91 on this policy - it is shown on the Transaction Detail tab but is deliberately EXCLUDED from this total. | | R14: United Auto|UAO694805
A15: Jorge | B15: YOANNY ALONSO M. | C15: Active | D15: New Business | E15: Personal Auto | F15: Progressive | G15: 875569393 | H15: 6/13/2026 | I15: 6 | J15: 1568 | K15: Progressive Detailed Statement 06/2026 | L15: =COUNTIF('Transaction Detail'!$A$2:$A$385,$R15) -> 1 | M15: 0.1 | N15: =SUMIF('Transaction Detail'!$A$2:$A$385,$R15,'Transaction Detail'!$N$2:$N$385) -> 1568 | O15: =SUMIF('Transaction Detail'!$A$2:$A$385,$R15,'Transaction Detail'!$O$2:$O$385) -> 156.8 | P15: =IF(N15=0,"",O15/N15) -> 0.1 | R15: Progressive|875569393
A16: Jorge | B16: YADIER CORDERO G. | C16: Active | D16: New Business | E16: Personal Auto | F16: United Auto | G16: UAO 695126 | H16: 6/15/2026 | I16: 12 | J16: 2268 | K16: United Insurance Group Direct Billing Stmt 06/2026 | L16: =COUNTIF('Transaction Detail'!$A$2:$A$385,$R16) -> 4 | M16: 0.1 | N16: =SUMIF('Transaction Detail'!$A$2:$A$385,$R16,'Transaction Detail'!$N$2:$N$385) -> 2485 | O16: =SUMIF('Transaction Detail'!$A$2:$A$385,$R16,'Transaction Detail'!$O$2:$O$385) -> 248.5 | P16: =IF(N16=0,"",O16/N16) -> 0.1 | Q16: Booked at 10% as collected. United also paid a separate 3% promotional incentive of $74.55 on this policy - it is shown on the Transaction Detail tab but is deliberately EXCLUDED from this total. | New Business 2,233.00 @ 10%; Endorsement 252.00 @ 10% | R16: United Auto|UAO695126
A17: Jorge | B17: STEPHANIE VAZQUEZ | C17: Active | D17: New Business | E17: Personal Auto | F17: United Auto | G17: UAO 695998 | H17: 6/19/2026 | I17: 12 | J17: 1122.35 | K17: United Insurance Group Direct Billing Stmt 06/2026 | L17: =COUNTIF('Transaction Detail'!$A$2:$A$385,$R17) -> 2 | M17: 0.1 | N17: =SUMIF('Transaction Detail'!$A$2:$A$385,$R17,'Transaction Detail'!$N$2:$N$385) -> 1079 | O17: =SUMIF('Transaction Detail'!$A$2:$A$385,$R17,'Transaction Detail'!$O$2:$O$385) -> 107.9 | P17: =IF(N17=0,"",O17/N17) -> 0.1 | Q17: Booked at 10% as collected. United also paid a separate 3% promotional incentive of $32.37 on this policy - it is shown on the Transaction Detail tab but is deliberately EXCLUDED from this total. | | R17: United Auto|UAO695998
A18: Jorge | B18: TAURUS L. PRESSLEY | C18: Active | D18: New Business | E18: Personal Auto | F18: Infinity | G18: 10270293001 | H18: 6/20/2026 | I18: 6 | J18: 820 | K18: Kemper Auto Monthly Producer Stmt 06/2026 | L18: =COUNTIF('Transaction Detail'!$A$2:$A$385,$R18) -> 1 | M18: 0.1 | N18: =SUMIF('Transaction Detail'!$A$2:$A$385,$R18,'Transaction Detail'!$N$2:$N$385) -> 810 | O18: =SUMIF('Transaction Detail'!$A$2:$A$385,$R18,'Transaction Detail'!$O$2:$O$385) -> 81 | P18: =IF(N18=0,"",O18/N18) -> 0.1 | R18: Infinity|10270293001
A19: Jorge | B19: ANTHONY PATTERSON | C19: Active | D19: New Business | E19: Personal Auto | F19: Progressive | G19: 875889820 | H19: 6/20/2026 | I19: 6 | J19: 1760 | K19: Progressive Detailed Statement 06/2026 | L19: =COUNTIF('Transaction Detail'!$A$2:$A$385,$R19) -> 2 | M19: 0.1 | N19: =SUMIF('Transaction Detail'!$A$2:$A$385,$R19,'Transaction Detail'!$N$2:$N$385) -> 1674 | O19: =SUMIF('Transaction Detail'!$A$2:$A$385,$R19,'Transaction Detail'!$O$2:$O$385) -> 167.4 | P19: =IF(N19=0,"",O19/N19) -> 0.1 | Q19: Credit Endorsement -86.00 @ 10%; New Business 1,760.00 @ 10% | R19: Progressive|875889820
A20: Jorge | B20: FELIPE GONZALEZ | C20: Active | D20: New Business | E20: Personal Auto | F20: Infinity | G20: 10270429601 | H20: 6/23/2026 | I20: 6 | J20: 1460 | K20: Kemper Auto Monthly Producer Stmt 06/2026 | L20: =COUNTIF('Transaction Detail'!$A$2:$A$385,$R20) -> 1 | M20: 0.1 | N20: =SUMIF('Transaction Detail'!$A$2:$A$385,$R20,'Transaction Detail'!$N$2:$N$385) -> 1450 | O20: =SUMIF('Transaction Detail'!$A$2:$A$385,$R20,'Transaction Detail'!$O$2:$O$385) -> 145 | P20: =IF(N20=0,"",O20/N20) -> 0.1 | R20: Infinity|10270429601
A21: Jorge | B21: CHRISTINA COSME | C21: Active | D21: New Business | E21: Personal Auto | F21: Progressive | G21: 876013327 | H21: 6/23/2026 | I21: 6 | J21: 1770 | K21: Progressive Detailed Statement 06/2026 | L21: =COUNTIF('Transaction Detail'!$A$2:$A$385,$R21) -> 1 | M21: 0.12 | N21: =SUMIF('Transaction Detail'!$A$2:$A$385,$R21,'Transaction Detail'!$N$2:$N$385) -> 1770 | O21: =SUMIF('Transaction Detail'!$A$2:$A$385,$R21,'Transaction Detail'!$O$2:$O$385) -> 212.4 | P21: =IF(N21=0,"",O21/N21) -> 0.12 | R21: Progressive|876013327
A22: Jorge | B22: CARLOS TABOADA | C22: Active | D22: New Business | E22: Personal Auto | F22: Progressive | G22: 876150583 | H22: 6/26/2026 | I22: 6 | J22: 370 | K22: Progressive Detailed Statement 06/2026 | L22: =COUNTIF('Transaction Detail'!$A$2:$A$385,$R22) -> 1 | M22: 0.1 | N22: =SUMIF('Transaction Detail'!$A$2:$A$385,$R22,'Transaction Detail'!$N$2:$N$385) -> 370 | O22: =SUMIF('Transaction Detail'!$A$2:$A$385,$R22,'Transaction Detail'!$O$2:$O$385) -> 37 | P22: =IF(N22=0,"",O22/N22) -> 0.1 | R22: Progressive|876150583
A23: Jorge | B23: MICHAEL D. HOWARD | C23: Active | D23: New Business | E23: Personal Auto | F23: United Auto | G23: UAO 697725 | H23: 6/27/2026 | I23: 6 | J23: 1406.35 | K23: United Insurance Group Direct Billing Stmt 06/2026 | L23: =COUNTIF('Transaction Detail'!$A$2:$A$385,$R23) -> 2 | M23: 0.1 | N23: =SUMIF('Transaction Detail'!$A$2:$A$385,$R23,'Transaction Detail'!$N$2:$N$385) -> 1373 | O23: =SUMIF('Transaction Detail'!$A$2:$A$385,$R23,'Transaction Detail'!$O$2:$O$385) -> 137.3 | P23: =IF(N23=0,"",O23/N23) -> 0.1 | Q23: Booked at 10% as collected. United also paid a separate 3% promotional incentive of $41.19 on this policy - it is shown on the Transaction Detail tab but is deliberately EXCLUDED from this total. | | R23: United Auto|UAO697725
A24: Jorge | B24: BRIANNA IRISH | C24: Active | D24: New Business | E24: Personal Auto | F24: Progressive | G24: 876186100 | H24: 6/26/2026 | I24: 6 | J24: 1994 | K24: Progressive Detailed Statement 06/2026 | L24: =COUNTIF('Transaction Detail'!$A$2:$A$385,$R24) -> 1 | M24: 0.1 | N24: =SUMIF('Transaction Detail'!$A$2:$A$385,$R24,'Transaction Detail'!$N$2:$N$385) -> 1994 | O24: =SUMIF('Transaction Detail'!$A$2:$A$385,$R24,'Transaction Detail'!$O$2:$O$385) -> 199.4 | P24: =IF(N24=0,"",O24/N24) -> 0.1 | R24: Progressive|876186100
B25: NEW BUSINESS SUBTOTAL | J25: =SUM(J7:J24) -> 29109.4 | N25: =SUM(N7:N24) -> 27628.89 | O25: =SUM(O7:O24) -> 2878.32 | P25: =IF(N25=0,"",O25/N25) -> 0.10417791
A27: RENEWALS
A28: Jorge | B28: AMARILLYS GONZALEZ | C28: Renewed | D28: Renewal | E28: Personal Auto | F28: Progressive | G28: 970306264 | H28: 6/1/2026 | I28: 6 | J28: 940 | K28: Progressive Detailed Statement 06/2026 | L28: =COUNTIF('Transaction Detail'!$A$2:$A$385,$R28) -> 0 | N28: =SUMIF('Transaction Detail'!$A$2:$A$385,$R28,'Transaction Detail'!$N$2:$N$385) -> 0 | O28: =SUMIF('Transaction Detail'!$A$2:$A$385,$R28,'Transaction Detail'!$O$2:$O$385) -> 0 | P28: =IF(N28=0,"",O28/N28) | Q28: Policy not found on the June 2026 Progressive statement - commission likely paid in a different statement period. | R28: Progressive|970306264
A29: Jorge | B29: BRUDYS GARCIA | C29: Renewed | D29: Renewal | E29: Personal Auto | F29: Progressive | G29: 990100610 | H29: 6/2/2026 | I29: 6 | J29: 1217 | K29: Progressive Detailed Statement 06/2026 | L29: =COUNTIF('Transaction Detail'!$A$2:$A$385,$R29) -> 0 | N29: =SUMIF('Transaction Detail'!$A$2:$A$385,$R29,'Transaction Detail'!$N$2:$N$385) -> 0 | O29: =SUMIF('Transaction Detail'!$A$2:$A$385,$R29,'Transaction Detail'!$O$2:$O$385) -> 0 | P29: =IF(N29=0,"",O29/N29) | Q29: Policy not found on the June 2026 Progressive statement - commission likely paid in a different statement period. | R29: Progressive|990100610
A30: Jorge | B30: YOSVANY LARRALDE | C30: Renewed | D30: Renewal | E30: Boat | F30: Progressive | G30: 982064065 | H30: 6/3/2026 | I30: 12 | J30: 719.12 | K30: Progressive Detailed Statement 06/2026 | L30: =COUNTIF('Transaction Detail'!$A$2:$A$385,$R30) -> 0 | N30: =SUMIF('Transaction Detail'!$A$2:$A$385,$R30,'Transaction Detail'!$N$2:$N$385) -> 0 | O30: =SUMIF('Transaction Detail'!$A$2:$A$385,$R30,'Transaction Detail'!$O$2:$O$385) -> 0 | P30: =IF(N30=0,"",O30/N30) | Q30: Policy not found on the June 2026 Progressive statement - commission likely paid in a different statement period. | R30: Progressive|982064065
A31: Jorge | B31: ANA G CASTANO | C31: Renewed | D31: Renewal | E31: Personal Auto | F31: Progressive | G31: 866496112 | H31: 6/3/2026 | I31: 6 | J31: 1023 | K31: Progressive Detailed Statement 06/2026 | L31: =COUNTIF('Transaction Detail'!$A$2:$A$385,$R31) -> 0 | N31: =SUMIF('Transaction Detail'!$A$2:$A$385,$R31,'Transaction Detail'!$N$2:$N$385) -> 0 | O31: =SUMIF('Transaction Detail'!$A$2:$A$385,$R31,'Transaction Detail'!$O$2:$O$385) -> 0 | P31: =IF(N31=0,"",O31/N31) | Q31: Policy not found on the June 2026 Progressive statement - commission likely paid in a different statement period. | R31: Progressive|866496112
A32: Jorge | B32: MANUEL MARTINEZ | C32: Renewed | D32: Renewal | E32: Personal Auto | F32: Progressive | G32: 990228513 | H32: 6/5/2026 | I32: 6 | J32: 3495 | K32: Progressive Detailed Statement 06/2026 | L32: =COUNTIF('Transaction Detail'!$A$2:$A$385,$R32) -> 0 | N32: =SUMIF('Transaction Detail'!$A$2:$A$385,$R32,'Transaction Detail'!$N$2:$N$385) -> 0 | O32: =SUMIF('Transaction Detail'!$A$2:$A$385,$R32,'Transaction Detail'!$O$2:$O$385) -> 0 | P32: =IF(N32=0,"",O32/N32) | Q32: Policy not found on the June 2026 Progressive statement - commission likely paid in a different statement period. | R32: Progressive|990228513
A33: Jorge | B33: NIEVES ABREU | C33: Renewed | D33: Renewal | E33: Personal Auto | F33: Progressive | G33: 866656050 | H33: 6/6/2026 | I33: 6 | J33: 2276 | K33: Progressive Detailed Statement 06/2026 | L33: =COUNTIF('Transaction Detail'!$A$2:$A$385,$R33) -> 1 | M33: 0.1 | N33: =SUMIF('Transaction Detail'!$A$2:$A$385,$R33,'Transaction Detail'!$N$2:$N$385) -> 2276 | O33: =SUMIF('Transaction Detail'!$A$2:$A$385,$R33,'Transaction Detail'!$O$2:$O$385) -> 227.6 | P33: =IF(N33=0,"",O33/N33) -> 0.1 | R33: Progressive|866656050
A34: Jorge | B34: IBET COLLADO | C34: Renewed | D34: Renewal | E34: Personal Auto | F34: Progressive | G34: 982208807 | H34: 6/6/2026 | I34: 6 | J34: 854 | K34: Progressive Detailed Statement 06/2026 | L34: =COUNTIF('Transaction Detail'!$A$2:$A$385,$R34) -> 1 | M34: 0.1 | N34: =SUMIF('Transaction Detail'!$A$2:$A$385,$R34,'Transaction Detail'!$N$2:$N$385) -> 854 | O34: =SUMIF('Transaction Detail'!$A$2:$A$385,$R34,'Transaction Detail'!$O$2:$O$385) -> 85.4 | P34: =IF(N34=0,"",O34/N34) -> 0.1 | R34: Progressive|982208807
A35: Jorge | B35: ALEJANDRO COLLADO | C35: Renewed | D35: Renewal | E35: Personal Auto | F35: Progressive | G35: 48745204 | H35: 6/7/2026 | I35: 6 | J35: 1956 | K35: Progressive Detailed Statement 06/2026 | L35: =COUNTIF('Transaction Detail'!$A$2:$A$385,$R35) -> 2 | M35: 0.1 | N35: =SUMIF('Transaction Detail'!$A$2:$A$385,$R35,'Transaction Detail'!$N$2:$N$385) -> 1355.77 | O35: =SUMIF('Transaction Detail'!$A$2:$A$385,$R35,'Transaction Detail'!$O$2:$O$385) -> 135.58 | P35: =IF(N35=0,"",O35/N35) -> 0.10000221 | Q35: Renewal 1,956.00 @ 10%; Credit Endorsement -600.23 @ 10% | R35: Progressive|48745204
A36: Jorge | B36: MANUELA GOMEZ OROZCO | C36: Renewed | D36: Renewal | E36: Personal Auto | F36: Progressive | G36: 866615155 | H36: 6/8/2026 | I36: 6 | J36: 2305 | K36: Progressive Detailed Statement 06/2026 | L36: =COUNTIF('Transaction Detail'!$A$2:$A$385,$R36) -> 1 | M36: 0.1 | N36: =SUMIF('Transaction Detail'!$A$2:$A$385,$R36,'Transaction Detail'!$N$2:$N$385) -> 2305 | O36: =SUMIF('Transaction Detail'!$A$2:$A$385,$R36,'Transaction Detail'!$O$2:$O$385) -> 230.5 | P36: =IF(N36=0,"",O36/N36) -> 0.1 | R36: Progressive|866615155
A37: Jorge | B37: REYSEL CASTILLO | C37: Renewed | D37: Renewal | E37: Boat | F37: Progressive | G37: 970570633 | H37: 6/9/2026 | I37: 12 | J37: 688.82 | K37: Progressive Detailed Statement 06/2026 | L37: =COUNTIF('Transaction Detail'!$A$2:$A$385,$R37) -> 0 | N37: =SUMIF('Transaction Detail'!$A$2:$A$385,$R37,'Transaction Detail'!$N$2:$N$385) -> 0 | O37: =SUMIF('Transaction Detail'!$A$2:$A$385,$R37,'Transaction Detail'!$O$2:$O$385) -> 0 | P37: =IF(N37=0,"",O37/N37) | Q37: Policy not found on the June 2026 Progressive statement - commission likely paid in a different statement period. | R37: Progressive|970570633
A38: Jorge | B38: ERIC CRUZ | C38: Renewed | D38: Renewal | E38: Personal Auto | F38: Progressive | G38: 998651589 | H38: 6/10/2026 | I38: 6 | J38: 2194 | K38: Progressive Detailed Statement 06/2026 | L38: =COUNTIF('Transaction Detail'!$A$2:$A$385,$R38) -> 1 | M38: 0.1 | N38: =SUMIF('Transaction Detail'!$A$2:$A$385,$R38,'Transaction Detail'!$N$2:$N$385) -> 2194 | O38: =SUMIF('Transaction Detail'!$A$2:$A$385,$R38,'Transaction Detail'!$O$2:$O$385) -> 219.4 | P38: =IF(N38=0,"",O38/N38) -> 0.1 | R38: Progressive|998651589
A39: Jorge | B39: JORGE A AGUIRRE MARIN | C39: Renewed | D39: Renewal | E39: Personal Auto | F39: Progressive | G39: 944684751 | H39: 6/11/2025 | I39: 6 | J39: 1906 | K39: Progressive Detailed Statement 06/2026 | L39: =COUNTIF('Transaction Detail'!$A$2:$A$385,$R39) -> 1 | M39: 0.1 | N39: =SUMIF('Transaction Detail'!$A$2:$A$385,$R39,'Transaction Detail'!$N$2:$N$385) -> 1906 | O39: =SUMIF('Transaction Detail'!$A$2:$A$385,$R39,'Transaction Detail'!$O$2:$O$385) -> 190.6 | P39: =IF(N39=0,"",O39/N39) -> 0.1 | R39: Progressive|944684751
A40: Jorge | B40: NATHAN R WALTERS | C40: Renewed | D40: Renewal | E40: Personal Auto | F40: Progressive | G40: 990565433 | H40: 6/13/2026 | I40: 6 | J40: 2083 | K40: Progressive Detailed Statement 06/2026 | L40: =COUNTIF('Transaction Detail'!$A$2:$A$385,$R40) -> 1 | M40: 0.1 | N40: =SUMIF('Transaction Detail'!$A$2:$A$385,$R40,'Transaction Detail'!$N$2:$N$385) -> 2083 | O40: =SUMIF('Transaction Detail'!$A$2:$A$385,$R40,'Transaction Detail'!$O$2:$O$385) -> 208.3 | P40: =IF(N40=0,"",O40/N40) -> 0.1 | R40: Progressive|990565433
A41: Jorge | B41: GUSTAVO F ALFONSO | C41: Renewed | D41: Renewal | E41: Personal Auto | F41: Progressive | G41: 975650843 | H41: 6/13/2026 | I41: 6 | J41: 1205 | K41: Progressive Detailed Statement 06/2026 | L41: =COUNTIF('Transaction Detail'!$A$2:$A$385,$R41) -> 1 | M41: 0.1 | N41: =SUMIF('Transaction Detail'!$A$2:$A$385,$R41,'Transaction Detail'!$N$2:$N$385) -> 1205 | O41: =SUMIF('Transaction Detail'!$A$2:$A$385,$R41,'Transaction Detail'!$O$2:$O$385) -> 120.5 | P41: =IF(N41=0,"",O41/N41) -> 0.1 | R41: Progressive|975650843
A42: Jorge | B42: CARMELO QUINTO | C42: Renewed | D42: Renewal | E42: Personal Auto | F42: Progressive | G42: 970707982 | H42: 6/14/2026 | I42: 6 | J42: 1278 | K42: Progressive Detailed Statement 06/2026 | L42: =COUNTIF('Transaction Detail'!$A$2:$A$385,$R42) -> 1 | M42: 0.1 | N42: =SUMIF('Transaction Detail'!$A$2:$A$385,$R42,'Transaction Detail'!$N$2:$N$385) -> 1278 | O42: =SUMIF('Transaction Detail'!$A$2:$A$385,$R42,'Transaction Detail'!$O$2:$O$385) -> 127.8 | P42: =IF(N42=0,"",O42/N42) -> 0.1 | R42: Progressive|970707982
A43: Jorge | B43: ERNESTO TORRES ARTOLA | C43: Renewed | D43: Renewal | E43: Personal Auto | F43: Progressive | G43: 866980392 | H43: 6/15/2026 | I43: 6 | J43: 539 | K43: Progressive Detailed Statement 06/2026 | L43: =COUNTIF('Transaction Detail'!$A$2:$A$385,$R43) -> 1 | M43: 0.1 | N43: =SUMIF('Transaction Detail'!$A$2:$A$385,$R43,'Transaction Detail'!$N$2:$N$385) -> 539 | O43: =SUMIF('Transaction Detail'!$A$2:$A$385,$R43,'Transaction Detail'!$O$2:$O$385) -> 53.9 | P43: =IF(N43=0,"",O43/N43) -> 0.1 | R43: Progressive|866980392
A44: Jorge | B44: NOEMI SANTANA GUERRA | C44: Renewed | D44: Renewal | E44: Personal Auto | F44: Progressive | G44: 867024300 | H44: 6/16/2026 | I44: 6 | J44: 945 | K44: Progressive Detailed Statement 06/2026 | L44: =COUNTIF('Transaction Detail'!$A$2:$A$385,$R44) -> 1 | M44: 0.1 | N44: =SUMIF('Transaction Detail'!$A$2:$A$385,$R44,'Transaction Detail'!$N$2:$N$385) -> 945 | O44: =SUMIF('Transaction Detail'!$A$2:$A$385,$R44,'Transaction Detail'!$O$2:$O$385) -> 94.5 | P44: =IF(N44=0,"",O44/N44) -> 0.1 | R44: Progressive|867024300
A45: Jorge | B45: ALEJANDRO RUIZ ABELLA | C45: Renewed | D45: Renewal | E45: Personal Auto | F45: Progressive | G45: 998666923 | H45: 6/16/2026 | I45: 6 | J45: 1213 | K45: Progressive Detailed Statement 06/2026 | L45: =COUNTIF('Transaction Detail'!$A$2:$A$385,$R45) -> 1 | M45: 0.1 | N45: =SUMIF('Transaction Detail'!$A$2:$A$385,$R45,'Transaction Detail'!$N$2:$N$385) -> 1213 | O45: =SUMIF('Transaction Detail'!$A$2:$A$385,$R45,'Transaction Detail'!$O$2:$O$385) -> 121.3 | P45: =IF(N45=0,"",O45/N45) -> 0.1 | R45: Progressive|998666923
A46: Jorge | B46: CRISTIAN BARROSO | C46: Renewed | D46: Renewal | E46: Personal Auto | F46: Progressive | G46: 970048369 | H46: 6/18/2026 | I46: 6 | J46: 794 | K46: Progressive Detailed Statement 06/2026 | L46: =COUNTIF('Transaction Detail'!$A$2:$A$385,$R46) -> 1 | M46: 0.1 | N46: =SUMIF('Transaction Detail'!$A$2:$A$385,$R46,'Transaction Detail'!$N$2:$N$385) -> 794 | O46: =SUMIF('Transaction Detail'!$A$2:$A$385,$R46,'Transaction Detail'!$O$2:$O$385) -> 79.4 | P46: =IF(N46=0,"",O46/N46) -> 0.1 | R46: Progressive|970048369
A47: Jorge | B47: JEAN R LAMOTHE | C47: Renewed | D47: Renewal | E47: Personal Auto | F47: Progressive | G47: 867210259 | H47: 6/20/2026 | I47: 6 | J47: 947 | K47: Progressive Detailed Statement 06/2026 | L47: =COUNTIF('Transaction Detail'!$A$2:$A$385,$R47) -> 1 | M47: 0.1 | N47: =SUMIF('Transaction Detail'!$A$2:$A$385,$R47,'Transaction Detail'!$N$2:$N$385) -> 947 | O47: =SUMIF('Transaction Detail'!$A$2:$A$385,$R47,'Transaction Detail'!$O$2:$O$385) -> 94.7 | P47: =IF(N47=0,"",O47/N47) -> 0.1 | R47: Progressive|867210259
A48: Jorge | B48: YALCIN ACIKDENIZ | C48: Renewed | D48: Renewal | E48: Motorcycle/ATV | F48: Progressive | G48: 982895397 | H48: 6/21/2026 | I48: 12 | J48: 949 | K48: Progressive Detailed Statement 06/2026 | L48: =COUNTIF('Transaction Detail'!$A$2:$A$385,$R48) -> 1 | M48: 0.1 | N48: =SUMIF('Transaction Detail'!$A$2:$A$385,$R48,'Transaction Detail'!$N$2:$N$385) -> 949 | O48: =SUMIF('Transaction Detail'!$A$2:$A$385,$R48,'Transaction Detail'!$O$2:$O$385) -> 94.9 | P48: =IF(N48=0,"",O48/N48) -> 0.1 | R48: Progressive|982895397
A49: Jorge | B49: JUAN N PEREZ | C49: Renewed | D49: Renewal | E49: Personal Auto | F49: Progressive | G49: 999181480 | H49: 6/21/2025 | I49: 6 | J49: 626 | K49: Progressive Detailed Statement 06/2026 | L49: =COUNTIF('Transaction Detail'!$A$2:$A$385,$R49) -> 1 | M49: 0.1 | N49: =SUMIF('Transaction Detail'!$A$2:$A$385,$R49,'Transaction Detail'!$N$2:$N$385) -> 619 | O49: =SUMIF('Transaction Detail'!$A$2:$A$385,$R49,'Transaction Detail'!$O$2:$O$385) -> 61.9 | P49: =IF(N49=0,"",O49/N49) -> 0.1 | R49: Progressive|999181480
... A56: Jorge | B56: YUSDELY JUNCO | C56: Renewed | D56: Renewal | E56: Personal Auto | F56: Ocean Harbor | G56: P020082739007 | H56: 6/14/2026 | I56: 6 | J56: 1176 | K56: Pearl Holding Group Commission Stmt 06/2026 | L56: =COUNTIF('Transaction Detail'!$A$2:$A$385,$R56) -> 1 | M56: 0.11 | N56: =SUMIF('Transaction Detail'!$A$2:$A$385,$R56,'Transaction Detail'!$N$2:$N$385) -> 1141 | O56: =SUMIF('Transaction Detail'!$A$2:$A$385,$R56,'Transaction Detail'!$O$2:$O$385) -> 125.51 | P56: =IF(N56=0,"",O56/N56) -> 0.11 | R56: Ocean Harbor|P20082739007
A57: Jorge | B57: SANDRA ZAMBRANA | C57: Renewed | D57: Renewal | E57: Personal Auto | F57: United Auto | G57: UAD 605735805 | H57: 6/14/2026 | I57: 6 | J57: 1133 | K57: United Insurance Group Direct Billing Stmt 06/2026 | L57: =COUNTIF('Transaction Detail'!$A$2:$A$385,$R57) -> 2 | M57: 0.1 | N57: =SUMIF('Transaction Detail'!$A$2:$A$385,$R57,'Transaction Detail'!$N$2:$N$385) -> 221.6 | O57: =SUMIF('Transaction Detail'!$A$2:$A$385,$R57,'Transaction Detail'!$O$2:$O$385) -> 22.16 | P57: =IF(N57=0,"",O57/N57) -> 0.1 | Q57: United bills this policy direct and pays AS COLLECTED, so June earns commission only on the premium United collected in June - more follows in later months. | Booked at 10% as collected. United also paid a separate 3% promotional incentive of $6.64 on this policy - it is shown on the Transaction Detail tab but is deliberately EXCLUDED from this total. | | R57: United Auto|UAD605735805
A58: Jorge | B58: TAMEKA GREENE | C58: Renewed | D58: Renewal | E58: Personal Auto | F58: United Auto | G58: UAO 44288703 | H58: 6/15/2026 | I58: 12 | J58: 1941 | K58: United Insurance Group Direct Billing Stmt 06/2026 | L58: =COUNTIF('Transaction Detail'!$A$2:$A$385,$R58) -> 2 | M58: 0.1 | N58: =SUMIF('Transaction Detail'!$A$2:$A$385,$R58,'Transaction Detail'!$N$2:$N$385) -> 162 | O58: =SUMIF('Transaction Detail'!$A$2:$A$385,$R58,'Transaction Detail'!$O$2:$O$385) -> 16.2 | P58: =IF(N58=0,"",O58/N58) -> 0.1 | Q58: United bills this policy direct and pays AS COLLECTED, so June earns commission only on the premium United collected in June - more follows in later months. | Booked at 10% as collected. United also paid a separate 3% promotional incentive of $4.86 on this policy - it is shown on the Transaction Detail tab but is deliberately EXCLUDED from this total. | | R58: United Auto|UAO44288703
A59: Jorge | B59: HECTOR LUIS RODRIGUEZ RAMOS | C59: Renewed | D59: Renewal | E59: Personal Auto | F59: United Auto | G59: UAE 20965001 | H59: 6/16/2026 | I59: 12 | J59: 2005 | K59: United Insurance Group Direct Billing Stmt 06/2026 | L59: =COUNTIF('Transaction Detail'!$A$2:$A$385,$R59) -> 2 | M59: 0.1 | N59: =SUMIF('Transaction Detail'!$A$2:$A$385,$R59,'Transaction Detail'!$N$2:$N$385) -> 147.7 | O59: =SUMIF('Transaction Detail'!$A$2:$A$385,$R59,'Transaction Detail'!$O$2:$O$385) -> 14.77 | P59: =IF(N59=0,"",O59/N59) -> 0.1 | Q59: United bills this policy direct and pays AS COLLECTED, so June earns commission only on the premium United collected in June - more follows in later months. | Booked at 10% as collected. United also paid a separate 3% promotional incentive of $4.43 on this policy - it is shown on the Transaction Detail tab but is deliberately EXCLUDED from this total. | | R59: United Auto|UAE20965001
A60: Jorge | B60: YAINELYS DIAZ SALAZAR | C60: Active | D60: Renewal | E60: Personal Auto | F60: United Auto | G60: UAO 653831 | H60: 12/19/2025 | I60: 12 | K60: United Insurance Group Direct Billing Stmt 06/2026 | L60: =COUNTIF('Transaction Detail'!$A$2:$A$385,$R60) -> 1 | M60: 0.1 | N60: =SUMIF('Transaction Detail'!$A$2:$A$385,$R60,'Transaction Detail'!$N$2:$N$385) -> 236.7 | O60: =SUMIF('Transaction Detail'!$A$2:$A$385,$R60,'Transaction Detail'!$O$2:$O$385) -> 23.67 | P60: =IF(N60=0,"",O60/N60) -> 0.1 | Q60: United bills this policy direct and pays AS COLLECTED, so June earns commission only on the premium United collected in June - more follows in later months. | | R60: United Auto|UAO653831
A61: Jorge | B61: CHRISTIAN O. CARBOT | C61: Active | D61: Renewal | E61: Personal Auto | F61: United Auto | G61: UAO 653867 | H61: 12/19/2025 | I61: 12 | K61: United Insurance Group Direct Billing Stmt 06/2026 | L61: =COUNTIF('Transaction Detail'!$A$2:$A$385,$R61) -> 1 | M61: 0.1 | N61: =SUMIF('Transaction Detail'!$A$2:$A$385,$R61,'Transaction Detail'!$N$2:$N$385) -> 359.7 | O61: =SUMIF('Transaction Detail'!$A$2:$A$385,$R61,'Transaction Detail'!$O$2:$O$385) -> 35.97 | P61: =IF(N61=0,"",O61/N61) -> 0.1 | Q61: United bills this policy direct and pays AS COLLECTED, so June earns commission only on the premium United collected in June - more follows in later months. | | R61: United Auto|UAO653867
A62: Jorge | B62: EDUARDO GOMES | C62: Renewed | D62: Renewal | E62: Personal Auto | F62: National General | G62: 2023332936 - 04 | H62: 6/1/2026 | I62: 6 | J62: 954 | K62: National General Commission Stmt 06/2026 | L62: =COUNTIF('Transaction Detail'!$A$2:$A$385,$R62) -> 3 | M62: 0.1 | N62: =SUMIF('Transaction Detail'!$A$2:$A$385,$R62,'Transaction Detail'!$N$2:$N$385) -> 919 | O62: =SUMIF('Transaction Detail'!$A$2:$A$385,$R62,'Transaction Detail'!$O$2:$O$385) -> 91.9 | P62: =IF(N62=0,"",O62/N62) -> 0.1 | Q62: Renew 401.00 @ 10%; Endorsement 650.00 @ 10%; Endorsement -132.00 @ 10% | R62: National General|202333293604
A63: Jorge | B63: ARMANDO CARALOS | C63: Active | D63: Renewal | E63: Personal Auto | F63: National General | G63: 2032597919 | H63: 12/9/2025 | I63: 12 | K63: National General Commission Stmt 06/2026 | L63: =COUNTIF('Transaction Detail'!$A$2:$A$385,$R63) -> 0 | N63: =SUMIF('Transaction Detail'!$A$2:$A$385,$R63,'Transaction Detail'!$N$2:$N$385) -> 0 | O63: =SUMIF('Transaction Detail'!$A$2:$A$385,$R63,'Transaction Detail'!$O$2:$O$385) -> 0 | P63: =IF(N63=0,"",O63/N63) | Q63: 12-month policy effective 12/9/2025; no June 2026 activity on the National General statement, so $0 is correct for this month. | R63: National General|2032597919
A64: Jorge | B64: EIGLYS M HERNANDEZ | C64: Renewed | D64: Renewal | E64: Personal Auto | F64: National General | G64: 2023520770 - 04 | H64: 6/13/2026 | I64: 6 | J64: 1450 | K64: National General Commission Stmt 06/2026 | L64: =COUNTIF('Transaction Detail'!$A$2:$A$385,$R64) -> 1 | M64: 0.1 | N64: =SUMIF('Transaction Detail'!$A$2:$A$385,$R64,'Transaction Detail'!$N$2:$N$385) -> 1415 | O64: =SUMIF('Transaction Detail'!$A$2:$A$385,$R64,'Transaction Detail'!$O$2:$O$385) -> 141.5 | P64: =IF(N64=0,"",O64/N64) -> 0.1 | R64: National General|202352077004
A65: Jorge | B65: JEFFREY B. PETIT-HOMME | C65: Renewed | D65: Renewal | E65: Personal Auto | F65: AmWins | G65: FFL01067788 | H65: 6/17/2026 | I65: 6 | J65: 921 | K65: Amwins Specialty Auto Commission Stmt 06/2026 | L65: =COUNTIF('Transaction Detail'!$A$2:$A$385,$R65) -> 1 | M65: 0.1 | N65: =SUMIF('Transaction Detail'!$A$2:$A$385,$R65,'Transaction Detail'!$N$2:$N$385) -> 178.5 | O65: =SUMIF('Transaction Detail'!$A$2:$A$385,$R65,'Transaction Detail'!$O$2:$O$385) -> 17.85 | P65: =IF(N65=0,"",O65/N65) -> 0.1 | R65: AmWins|FFL1067788
A66: Jorge | B66: ANGELY GEJO | C66: Renewed | D66: Renewal | E66: Personal Auto | F66: AmWins | G66: FFL01008512 | H66: 6/29/2026 | I66: 6 | J66: 1065 | K66: Amwins Specialty Auto Commission Stmt 06/2026 | L66: =COUNTIF('Transaction Detail'!$A$2:$A$385,$R66) -> 1 | M66: 0.1 | N66: =SUMIF('Transaction Detail'!$A$2:$A$385,$R66,'Transaction Detail'!$N$2:$N$385) -> 164.67 | O66: =SUMIF('Transaction Detail'!$A$2:$A$385,$R66,'Transaction Detail'!$O$2:$O$385) -> 16.47 | P66: =IF(N66=0,"",O66/N66) -> 0.10001822 | R66: AmWins|FFL1008512
A67: Jorge | B67: LUIS QUINONES SANCHEZ | C67: Renewed | D67: Renewal | E67: Personal Auto | F67: AmWins | G67: FFL01033783 | H67: 6/30/2026 | I67: 6 | J67: 315 | K67: Amwins Specialty Auto Commission Stmt 06/2026 | L67: =COUNTIF('Transaction Detail'!$A$2:$A$385,$R67) -> 1 | M67: 0.1 | N67: =SUMIF('Transaction Detail'!$A$2:$A$385,$R67,'Transaction Detail'!$N$2:$N$385) -> 77.5 | O67: =SUMIF('Transaction Detail'!$A$2:$A$385,$R67,'Transaction Detail'!$O$2:$O$385) -> 7.75 | P67: =IF(N67=0,"",O67/N67) -> 0.1 | R67: AmWins|FFL1033783
A68: Jorge | B68: LEVY DIAZ TORRES (no business name yet) | C68: Active | D68: Renewal | E68: Commercial Auto | F68: Infinity | G68: 50028915301 | H68: 12/1/2025 | I68: 12 | K68: Kemper Auto Monthly Producer Stmt 06/2026 | L68: =COUNTIF('Transaction Detail'!$A$2:$A$385,$R68) -> 0 | N68: =SUMIF('Transaction Detail'!$A$2:$A$385,$R68,'Transaction Detail'!$N$2:$N$385) -> 0 | O68: =SUMIF('Transaction Detail'!$A$2:$A$385,$R68,'Transaction Detail'!$O$2:$O$385) -> 0 | P68: =IF(N68=0,"",O68/N68) | Q68: 12-month policy effective 12/1/2025; no June 2026 activity on the Infinity statement, so $0 is correct for this month. | R68: Infinity|50028915301
A69: Jorge | B69: ELIZABETH MIRABAL HERNANDEZ (YSC LUXE BEAUTY) | C69: Active | D69: Renewal | E69: Commercial Auto | F69: Infinity | G69: 50029076701 | H69: 12/6/2025 | I69: 12 | K69: Kemper Auto Monthly Producer Stmt 06/2026 | L69: =COUNTIF('Transaction Detail'!$A$2:$A$385,$R69) -> 0 | N69: =SUMIF('Transaction Detail'!$A$2:$A$385,$R69,'Transaction Detail'!$N$2:$N$385) -> 0 | O69: =SUMIF('Transaction Detail'!$A$2:$A$385,$R69,'Transaction Detail'!$O$2:$O$385) -> 0 | P69: =IF(N69=0,"",O69/N69) | Q69: 12-month policy effective 12/6/2025; no June 2026 activity on the Infinity statement, so $0 is correct for this month. | R69: Infinity|50029076701
A70: Jorge | B70: ANA MARIA ACOSTA | C70: Active | D70: Renewal | E70: Personal Auto | F70: Infinity | G70: 10210540801 | H70: 12/7/2025 | I70: 12 | K70: Kemper Auto Monthly Producer Stmt 06/2026 | L70: =COUNTIF('Transaction Detail'!$A$2:$A$385,$R70) -> 0 | N70: =SUMIF('Transaction Detail'!$A$2:$A$385,$R70,'Transaction Detail'!$N$2:$N$385) -> 0 | O70: =SUMIF('Transaction Detail'!$A$2:$A$385,$R70,'Transaction Detail'!$O$2:$O$385) -> 0 | P70: =IF(N70=0,"",O70/N70) | Q70: 12-month policy effective 12/7/2025; no June 2026 activity on the Infinity statement, so $0 is correct for this month. | R70: Infinity|10210540801
A71: Jorge | B71: MANUEL VERA | C71: Renewed | D71: Renewal | E71: Personal Auto | F71: Infinity | G71: 10074082701 | H71: 6/13/2026 | I71: 6 | J71: 1425 | K71: Kemper Auto Monthly Producer Stmt 06/2026 | L71: =COUNTIF('Transaction Detail'!$A$2:$A$385,$R71) -> 1 | M71: 0.1 | N71: =SUMIF('Transaction Detail'!$A$2:$A$385,$R71,'Transaction Detail'!$N$2:$N$385) -> 1425 | O71: =SUMIF('Transaction Detail'!$A$2:$A$385,$R71,'Transaction Detail'!$O$2:$O$385) -> 142.5 | P71: =IF(N71=0,"",O71/N71) -> 0.1 | R71: Infinity|10074082701
A72: Jorge | B72: JAMES JOHN CIULLO | C72: Active | D72: Renewal | E72: Personal Auto | F72: Infinity | G72: 10212418501 | H72: 12/23/2025 | I72: 12 | K72: Kemper Auto Monthly Producer Stmt 06/2026 | L72: =COUNTIF('Transaction Detail'!$A$2:$A$385,$R72) -> 0 | N72: =SUMIF('Transaction Detail'!$A$2:$A$385,$R72,'Transaction Detail'!$N$2:$N$385) -> 0 | O72: =SUMIF('Transaction Detail'!$A$2:$A$385,$R72,'Transaction Detail'!$O$2:$O$385) -> 0 | P72: =IF(N72=0,"",O72/N72) | Q72: 12-month policy effective 12/23/2025; no June 2026 activity on the Infinity statement, so $0 is correct for this month. | R72: Infinity|10212418501
B73: RENEWALS SUBTOTAL | J73: =SUM(J28:J72) -> 49272.55 | N73: =SUM(N28:N72) -> 34604.14 | O73: =SUM(O28:O72) -> 3483.36 | P73: =IF(N73=0,"",O73/N73) -> 0.1006631
B75: JUNE BINDER SHEET TOTAL | J75: =J25+J73 -> 78381.95 | N75: =N25+N73 -> 62233.03 | O75: =O25+O73 -> 6361.68 | P75: =IF(N75=0,"",O75/N75) -> 0.10222353
A77: OTHER DORAL BOOK ACTIVITY - policies from the wider book with June statement activity
A78: Jorge | B78: IVAN D MOLINA LOZANO | C78: FEB 26 | D78: Book activity | E78: Progressive | F78: Progressive | G78: 862085078 | K78: Progressive Detailed Statement 06/2026 | L78: =COUNTIF('Book Activity by Carrier'!$B$5:$B$129,$G78) -> 1 | M78: 0.1 | N78: =SUMIF('Book Activity by Carrier'!$B$5:$B$129,$G78,'Book Activity by Carrier'!$G$5:$G$129) -> 299.97 | O78: =SUMIF('Book Activity by Carrier'!$B$5:$B$129,$G78,'Book Activity by Carrier'!$J$5:$J$129) -> 30 | P78: =IF(N78=0,"",O78/N78) -> 0.10001 | Q78: Endorsement 299.97 @ 10%
A79: Jorge | B79: GUILLERMO FAYAS RODRIGUEZ | C79: JULY 26 | D79: Book activity | E79: Progressive | F79: Progressive | G79: 867943703 | K79: Progressive Detailed Statement 06/2026 | L79: =COUNTIF('Book Activity by Carrier'!$B$5:$B$129,$G79) -> 1 | M79: 0.1 | N79: =SUMIF('Book Activity by Carrier'!$B$5:$B$129,$G79,'Book Activity by Carrier'!$G$5:$G$129) -> 1794 | O79: =SUMIF('Book Activity by Carrier'!$B$5:$B$129,$G79,'Book Activity by Carrier'!$J$5:$J$129) -> 179.4 | P79: =IF(N79=0,"",O79/N79) -> 0.1 | Q79: Renewal 1,794.00 @ 10%
A80: Jorge | B80: KATHERINE A FERNANDEZ | C80: FEB 26 | D80: Book activity | E80: Progressive | F80: Progressive | G80: 869341373 | K80: Progressive Detailed Statement 06/2026 | L80: =COUNTIF('Book Activity by Carrier'!$B$5:$B$129,$G80) -> 1 | M80: 0.1 | N80: =SUMIF('Book Activity by Carrier'!$B$5:$B$129,$G80,'Book Activity by Carrier'!$G$5:$G$129) -> -592.29 | O80: =SUMIF('Book Activity by Carrier'!$B$5:$B$129,$G80,'Book Activity by Carrier'!$J$5:$J$129) -> -59.23 | P80: =IF(N80=0,"",O80/N80) -> 0.10000169 | Q80: Cancel Pro Rate -592.29 @ 10%
A81: Jorge | B81: IVAN S FLORES JARAMILLO | C81: FEB 26 | D81: Book activity | E81: Progressive | F81: Progressive | G81: 869745230 | K81: Progressive Detailed Statement 06/2026 | L81: =COUNTIF('Book Activity by Carrier'!$B$5:$B$129,$G81) -> 1 | M81: 0.1 | N81: =SUMIF('Book Activity by Carrier'!$B$5:$B$129,$G81,'Book Activity by Carrier'!$G$5:$G$129) -> 0 | O81: =SUMIF('Book Activity by Carrier'!$B$5:$B$129,$G81,'Book Activity by Carrier'!$J$5:$J$129) -> 0 | P81: =IF(N81=0,"",O81/N81) | Q81: Endorsement 0.00 @ 10%
A82: Jorge | B82: CAROL J SAFI | C82: data march | D82: Book activity | E82: Progressive | F82: Progressive | G82: 871135598 | K82: Progressive Detailed Statement 06/2026 | L82: =COUNTIF('Book Activity by Carrier'!$B$5:$B$129,$G82) -> 1 | M82: 0.1 | N82: =SUMIF('Book Activity by Carrier'!$B$5:$B$129,$G82,'Book Activity by Carrier'!$G$5:$G$129) -> -133.12 | O82: =SUMIF('Book Activity by Carrier'!$B$5:$B$129,$G82,'Book Activity by Carrier'!$J$5:$J$129) -> -13.31 | P82: =IF(N82=0,"",O82/N82) -> 0.099984976 | Q82: Credit Endorsement -133.12 @ 10%
A83: Jorge | B83: JUAN J ORTUNO | C83: data march | D83: Book activity | E83: Progressive | F83: Progressive | G83: 871466655 | K83: Progressive Detailed Statement 06/2026 | L83: =COUNTIF('Book Activity by Carrier'!$B$5:$B$129,$G83) -> 1 | M83: 0.1 | N83: =SUMIF('Book Activity by Carrier'!$B$5:$B$129,$G83,'Book Activity by Carrier'!$G$5:$G$129) -> -26.08 | O83: =SUMIF('Book Activity by Carrier'!$B$5:$B$129,$G83,'Book Activity by Carrier'!$J$5:$J$129) -> -2.61 | P83: =IF(N83=0,"",O83/N83) -> 0.10007669 | Q83: Credit Endorsement -26.08 @ 10%
A84: Jorge | B84: DAVID GUERRA | C84: data april | D84: Book activity | E84: Progressive | F84: Progressive | G84: 872036378 | K84: Progressive Detailed Statement 06/2026 | L84: =COUNTIF('Book Activity by Carrier'!$B$5:$B$129,$G84) -> 1 | M84: 0.12 | N84: =SUMIF('Book Activity by Carrier'!$B$5:$B$129,$G84,'Book Activity by Carrier'!$G$5:$G$129) -> -736.55 | O84: =SUMIF('Book Activity by Carrier'!$B$5:$B$129,$G84,'Book Activity by Carrier'!$J$5:$J$129) -> -88.39 | P84: =IF(N84=0,"",O84/N84) -> 0.12000543 | Q84: Cancel Pro Rate -736.55 @ 12%
A85: Jorge | B85: PAULINA GUERRERO | C85: data april | D85: Book activity | E85: Progressive | F85: Progressive | G85: 872333790 | K85: Progressive Detailed Statement 06/2026 | L85: =COUNTIF('Book Activity by Carrier'!$B$5:$B$129,$G85) -> 1 | M85: 0.1 | N85: =SUMIF('Book Activity by Carrier'!$B$5:$B$129,$G85,'Book Activity by Carrier'!$G$5:$G$129) -> -579.3 | O85: =SUMIF('Book Activity by Carrier'!$B$5:$B$129,$G85,'Book Activity by Carrier'!$J$5:$J$129) -> -57.93 | P85: =IF(N85=0,"",O85/N85) -> 0.1 | Q85: Cancel Pro Rate -579.30 @ 10%
A86: Jorge | B86: JOSE MICO I. | C86: data april | D86: Book activity | E86: Progressive | F86: Progressive | G86: 872526456 | K86: Progressive Detailed Statement 06/2026 | L86: =COUNTIF('Book Activity by Carrier'!$B$5:$B$129,$G86) -> 2 | M86: 0.1 | N86: =SUMIF('Book Activity by Carrier'!$B$5:$B$129,$G86,'Book Activity by Carrier'!$G$5:$G$129) -> -1313.54 | O86: =SUMIF('Book Activity by Carrier'!$B$5:$B$129,$G86,'Book Activity by Carrier'!$J$5:$J$129) -> -131.36 | P86: =IF(N86=0,"",O86/N86) -> 0.10000457 | Q86: Endorsement 100.14 @ 10%; Cancel Pro Rate -1,413.68 @ 10%
A87: Jorge | B87: ROSS M LAZAREK | C87: data april | D87: Book activity | E87: Progressive | F87: Progressive | G87: 873197162 | K87: Progressive Detailed Statement 06/2026 | L87: =COUNTIF('Book Activity by Carrier'!$B$5:$B$129,$G87) -> 1 | M87: 0.14 | N87: =SUMIF('Book Activity by Carrier'!$B$5:$B$129,$G87,'Book Activity by Carrier'!$G$5:$G$129) -> -33.64 | O87: =SUMIF('Book Activity by Carrier'!$B$5:$B$129,$G87,'Book Activity by Carrier'!$J$5:$J$129) -> -4.71 | P87: =IF(N87=0,"",O87/N87) -> 0.14001189 | Q87: Credit Endorsement -33.64 @ 14%
A88: Jorge | B88: JOSE DIAZ | C88: data may | D88: Book activity | E88: Progressive | F88: Progressive | G88: 874616317 | K88: Progressive Detailed Statement 06/2026 | L88: =COUNTIF('Book Activity by Carrier'!$B$5:$B$129,$G88) -> 1 | M88: 0.1 | N88: =SUMIF('Book Activity by Carrier'!$B$5:$B$129,$G88,'Book Activity by Carrier'!$G$5:$G$129) -> -744.72 | O88: =SUMIF('Book Activity by Carrier'!$B$5:$B$129,$G88,'Book Activity by Carrier'!$J$5:$J$129) -> -74.47 | P88: =IF(N88=0,"",O88/N88) -> 0.099997314 | Q88: Cancel Pro Rate -744.72 @ 10%
A89: Jorge | B89: MELISSA A TAYLOR | C89: JULY 26 | D89: Book activity | E89: Progressive | F89: Progressive | G89: 876394907 | K89: Progressive Detailed Statement 06/2026 | L89: =COUNTIF('Book Activity by Carrier'!$B$5:$B$129,$G89) -> 2 | M89: 0.12 | N89: =SUMIF('Book Activity by Carrier'!$B$5:$B$129,$G89,'Book Activity by Carrier'!$G$5:$G$129) -> 1227 | O89: =SUMIF('Book Activity by Carrier'!$B$5:$B$129,$G89,'Book Activity by Carrier'!$J$5:$J$129) -> 147.24 | P89: =IF(N89=0,"",O89/N89) -> 0.12 | Q89: Credit Endorsement -177.00 @ 12%; New Business 1,404.00 @ 12%
... A142: Jorge | B142: IRIS LOPEZ SANCHEZ | C142: geico | D142: Book activity | E142: Geico | F142: GEICO | G142: 6219586788-442580316 | K142: GEICO Commission Statement 06/2026 | L142: =COUNTIF('Book Activity by Carrier'!$B$5:$B$129,$G142) -> 2 | M142: 0.12 | N142: =SUMIF('Book Activity by Carrier'!$B$5:$B$129,$G142,'Book Activity by Carrier'!$G$5:$G$129) -> -381.54 | O142: =SUMIF('Book Activity by Carrier'!$B$5:$B$129,$G142,'Book Activity by Carrier'!$J$5:$J$129) -> -45.78 | P142: =IF(N142=0,"",O142/N142) -> 0.11998742 | Q142: Renewal Year Commission -402.75 @ 12%; Renewal Year Commission 21.21 @ 12%
B143: OTHER BOOK ACTIVITY SUBTOTAL | N143: =SUM(N78:N142) -> -15809.4 | O143: =SUM(O78:O142) -> -1593.97 | P143: =IF(N143=0,"",O143/N143) -> 0.10082419
A145: STATEMENT ADJUSTMENTS & FEES - every chargeback and fee the carriers apply outside the policy listing. Shaded rows could not be tied to a Doral client and are NOT counted.
B146: UW Reports fee FL - 23 | D146: Adjustment | E146: Fee - UW Reports | F146: Infinity | G146: Agent 5517897 | H146: 06/30/2026 | K146: Kemper Auto Monthly Producer Stmt 06/2026 | L146: 1 | N146: -10.35 | O146: 0 | Q146: NOT COUNTED - Agency-level fee - Kemper names no insured, so it cannot be attributed to the Doral book
B147: UW Reports fee FL - 90 | D147: Adjustment | E147: Fee - UW Reports | F147: Infinity | G147: Agent 5517897 | H147: 06/30/2026 | K147: Kemper Auto Monthly Producer Stmt 06/2026 | L147: 1 | N147: -22.55 | O147: 0 | Q147: NOT COUNTED - Agency-level fee - Kemper names no insured, so it cannot be attributed to the Doral book
B148: 3% promotional incentive on June binder-sheet policies | C148: 9 lines | D148: Adjustment | E148: Promotional Incentive | F148: United Auto | G148: Agent 001-1D-100208 | H148: 06/30/26 | K148: United Insurance Group Direct Billing Stmt 06/2026 | L148: 1 | N148: 252.85 | O148: 0 | Q148: NOT COUNTED - United books its 3% incentive as an Adjustment (its statement shows 37 such lines netting $6.89 agency-wide). Excluded by instruction - this book is carried at 10% as collected. Every line is itemised on the Transaction Detail and Book Activity tabs.
B149: 3% promotional incentive on wider Doral book policies | C149: 23 lines | D149: Adjustment | E149: Promotional Incentive | F149: United Auto | G149: Agent 001-1D-100208 | H149: 06/30/26 | K149: United Insurance Group Direct Billing Stmt 06/2026 | L149: 1 | N149: -266.32 | O149: 0 | Q149: NOT COUNTED - United books its 3% incentive as an Adjustment (its statement shows 37 such lines netting $6.89 agency-wide). Excluded by instruction - this book is carried at 10% as collected. Every line is itemised on the Transaction Detail and Book Activity tabs.
A150: Jorge | B150: JAHMAR JOHNSON | C150: JULY 26 | D150: Adjustment | E150: MVR Cost | F150: Ocean Harbor | G150: Producer 6883 | H150: 06/22/2026 | K150: Pearl Holding Group Commission Stmt 06/2026 | L150: 1 | N150: -8.36 | O150: -8.36 | Q150: Name abbreviated by Pearl; matched to Jahmar J Johnson, who is on this same statement
B151: MARTINEZ, L | D151: Adjustment | E151: MVR Cost | F151: Ocean Harbor | G151: Producer 6883 | H151: 06/05/2026 | K151: Pearl Holding Group Commission Stmt 06/2026 | L151: 1 | N151: -8.36 | O151: 0 | Q151: NOT COUNTED - Name abbreviated by Pearl - no confident Doral match
A152: Jorge | B152: JOSE ABREU | C152: JULY 26 | D152: Adjustment | E152: Viol Hist Chargeback | F152: National General | G152: Quote 242804983 | H152: 4/9/2026 | K152: National General Commission Stmt 06/2026 | L152: 1 | N152: -9.02 | O152: -9.02 | Q152: Matched by name and quote number - this section carries no policy number
A153: Jorge | B153: CHARLIE HOZ | C153: data april | D153: Adjustment | E153: Loss Hist Chargeback | F153: National General | G153: Quote 245836859 | H153: 4/28/2026 | K153: National General Commission Stmt 06/2026 | L153: 1 | N153: -1 | O153: -1 | Q153: Matched by name and quote number - this section carries no policy number
A154: Jorge | B154: FERNANDO RODRIGUEZ | C154: FEB 24 | D154: Adjustment | E154: Loss Hist Chargeback | F154: National General | G154: Quote 242948950 | H154: 4/10/2026 | K154: National General Commission Stmt 06/2026 | L154: 1 | N154: -1 | O154: -1 | Q154: Matched by name and quote number - this section carries no policy number
A155: Jorge | B155: GAVONEEY Q. WILSON | C155: data april | D155: Adjustment | E155: Loss Hist Chargeback | F155: National General | G155: Quote 242639442 | H155: 4/8/2026 | K155: National General Commission Stmt 06/2026 | L155: 1 | N155: -1 | O155: -1 | Q155: Matched by name and quote number - this section carries no policy number
A156: Jorge | B156: JOSE ABREU | C156: JULY 26 | D156: Adjustment | E156: Loss Hist Chargeback | F156: National General | G156: Quote 242804983 | H156: 4/9/2026 | K156: National General Commission Stmt 06/2026 | L156: 1 | N156: -1 | O156: -1 | Q156: Matched by name and quote number - this section carries no policy number
A157: Jorge | B157: JULIO OVIOL | C157: data april | D157: Adjustment | E157: Loss Hist Chargeback | F157: National General | G157: Quote 244079950 | H157: 4/17/2026 | K157: National General Commission Stmt 06/2026 | L157: 1 | N157: -1 | O157: -1 | Q157: Matched by name and quote number - this section carries no policy number
A158: Jorge | B158: KIMBERLY MUNIZ | C158: data april | D158: Adjustment | E158: Loss Hist Chargeback | F158: National General | G158: Quote 242985155 | H158: 4/10/2026 | K158: National General Commission Stmt 06/2026 | L158: 1 | N158: -1 | O158: -1 | Q158: Matched by name and quote number - this section carries no policy number
A159: Jorge | B159: LENIN PEREZ PEREZ | C159: OCT 25 | D159: Adjustment | E159: Loss Hist Chargeback | F159: National General | G159: Quote 246190349 | H159: 4/30/2026 | K159: National General Commission Stmt 06/2026 | L159: 1 | N159: -1 | O159: -1 | Q159: Matched by name and quote number - this section carries no policy number
A160: Jorge | B160: JOSE ABREU | C160: JULY 26 | D160: Adjustment | E160: Viol Hist Chargeback | F160: National General | G160: Quote 242804983 | H160: 4/9/2026 | K160: National General Commission Stmt 06/2026 | L160: 1 | N160: -9.02 | O160: -9.02 | Q160: Matched by name and quote number - this section carries no policy number
A161: Jorge | B161: MIRLOUDE PETIT FRERE | C161: data april | D161: Adjustment | E161: Loss Hist Chargeback | F161: National General | G161: Quote 244094116 | H161: 4/17/2026 | K161: National General Commission Stmt 06/2026 | L161: 1 | N161: -1 | O161: -1 | Q161: Matched by name and quote number - this section carries no policy number
A162: Jorge | B162: KIMBERLY MUNIZ | C162: data april | D162: Adjustment | E162: Viol Hist Chargeback | F162: National General | G162: Quote 242985155 | H162: 4/10/2026 | K162: National General Commission Stmt 06/2026 | L162: 1 | N162: -9.02 | O162: -9.02 | Q162: Matched by name and quote number - this section carries no policy number
B163: Adrian Rodriguez | D163: Adjustment | E163: Loss Hist Chargeback | F163: National General | G163: Quote 242611771 | H163: 4/8/2026 | K163: National General Commission Stmt 06/2026 | L163: 1 | N163: -1 | O163: 0 | Q163: NOT COUNTED - Matched by name and quote number - this section carries no policy number
...

Sheet Transaction Detail
A1: Match Key | B1: Carrier | C1: Commission Statement | D1: Statement Policy # | E1: Insured Name (per statement) | F1: Transaction Type | G1: Transaction Date | H1: Written / Gross Premium | I1: Commissionable Basis | J1: Carrier Comm Rate | K1: Commission per Statement | L1: Check: Basis x Rate | M1: Diff | N1: Premium Counted in Summary | O1: Commission Counted in Summary | P1: In Doral Binder Book? | Q1: Binder Customer Name
A2: Progressive|48745204 | B2: Progressive | C2: Progressive Detailed Statement 06/2026 | D2: 48745204 | E2: COLLADO A. | F2: Renewal | G2: 06/07/2026 | H2: 1956 | I2: 1956 | J2: 0.1 | K2: 195.6 | L2: =ROUND(I2*J2,2) -> 195.6 | M2: =K2-L2 -> 0 | N2: =IF(F2="Promotional Incentive",0,I2) -> 1956 | O2: =IF(F2="Promotional Incentive",0,K2) -> 195.6 | P2: YES | Q2: ALEJANDRO COLLADO
A3: Progressive|48745204 | B3: Progressive | C3: Progressive Detailed Statement 06/2026 | D3: 48745204 | E3: COLLADO A. | F3: Credit Endorsement | G3: 06/10/2026 | H3: -600.23 | I3: -600.23 | J3: 0.1 | K3: -60.02 | L3: =ROUND(I3*J3,2) -> -60.02 | M3: =K3-L3 -> 0 | N3: =IF(F3="Promotional Incentive",0,I3) -> -600.23 | O3: =IF(F3="Promotional Incentive",0,K3) -> -60.02 | P3: YES | Q3: ALEJANDRO COLLADO
A4: Progressive|866615155 | B4: Progressive | C4: Progressive Detailed Statement 06/2026 | D4: 866615155 | E4: GOMEZ OROZCO M. | F4: Renewal | G4: 06/08/2026 | H4: 2305 | I4: 2305 | J4: 0.1 | K4: 230.5 | L4: =ROUND(I4*J4,2) -> 230.5 | M4: =K4-L4 -> 0 | N4: =IF(F4="Promotional Incentive",0,I4) -> 2305 | O4: =IF(F4="Promotional Incentive",0,K4) -> 230.5 | P4: YES | Q4: MANUELA GOMEZ OROZCO
A5: Progressive|866656050 | B5: Progressive | C5: Progressive Detailed Statement 06/2026 | D5: 866656050 | E5: ABREU N. | F5: Renewal | G5: 06/06/2026 | H5: 2276 | I5: 2276 | J5: 0.1 | K5: 227.6 | L5: =ROUND(I5*J5,2) -> 227.6 | M5: =K5-L5 -> 0 | N5: =IF(F5="Promotional Incentive",0,I5) -> 2276 | O5: =IF(F5="Promotional Incentive",0,K5) -> 227.6 | P5: YES | Q5: NIEVES ABREU
A6: Progressive|866980392 | B6: Progressive | C6: Progressive Detailed Statement 06/2026 | D6: 866980392 | E6: TORRES ARTOL E. | F6: Renewal | G6: 06/15/2026 | H6: 539 | I6: 539 | J6: 0.1 | K6: 53.9 | L6: =ROUND(I6*J6,2) -> 53.9 | M6: =K6-L6 -> 0 | N6: =IF(F6="Promotional Incentive",0,I6) -> 539 | O6: =IF(F6="Promotional Incentive",0,K6) -> 53.9 | P6: YES | Q6: ERNESTO TORRES ARTOLA
A7: Progressive|867024300 | B7: Progressive | C7: Progressive Detailed Statement 06/2026 | D7: 867024300 | E7: SANTANA GUER N. | F7: Renewal | G7: 06/16/2026 | H7: 945 | I7: 945 | J7: 0.1 | K7: 94.5 | L7: =ROUND(I7*J7,2) -> 94.5 | M7: =K7-L7 -> 0 | N7: =IF(F7="Promotional Incentive",0,I7) -> 945 | O7: =IF(F7="Promotional Incentive",0,K7) -> 94.5 | P7: YES | Q7: NOEMI SANTANA GUERRA
A8: Progressive|867210259 | B8: Progressive | C8: Progressive Detailed Statement 06/2026 | D8: 867210259 | E8: LAMOTHE J. | F8: Renewal | G8: 06/20/2026 | H8: 947 | I8: 947 | J8: 0.1 | K8: 94.7 | L8: =ROUND(I8*J8,2) -> 94.7 | M8: =K8-L8 -> 0 | N8: =IF(F8="Promotional Incentive",0,I8) -> 947 | O8: =IF(F8="Promotional Incentive",0,K8) -> 94.7 | P8: YES | Q8: JEAN R LAMOTHE
A9: Progressive|875244202 | B9: Progressive | C9: Progressive Detailed Statement 06/2026 | D9: 875244202 | E9: QUIROZ G. | F9: New Business | G9: 06/06/2026 | H9: 1175 | I9: 1175 | J9: 0.12 | K9: 141 | L9: =ROUND(I9*J9,2) -> 141 | M9: =K9-L9 -> 0 | N9: =IF(F9="Promotional Incentive",0,I9) -> 1175 | O9: =IF(F9="Promotional Incentive",0,K9) -> 141 | P9: YES | Q9: GREGORIO QUIROZ
A10: Progressive|875310026 | B10: Progressive | C10: Progressive Detailed Statement 06/2026 | D10: 875310026 | E10: RAMIREZ J. | F10: Credit Endorsement | G10: 06/08/2026 | H10: -277 | I10: -277 | J10: 0.14 | K10: -38.78 | L10: =ROUND(I10*J10,2) -> -38.78 | M10: =K10-L10 -> 0 | N10: =IF(F10="Promotional Incentive",0,I10) -> -277 | O10: =IF(F10="Promotional Incentive",0,K10) -> -38.78 | P10: YES | Q10: JULIO RAMIREZ
A11: Progressive|875310026 | B11: Progressive | C11: Progressive Detailed Statement 06/2026 | D11: 875310026 | E11: RAMIREZ J. | F11: New Business | G11: 06/08/2026 | H11: 1935 | I11: 1935 | J11: 0.14 | K11: 270.9 | L11: =ROUND(I11*J11,2) -> 270.9 | M11: =K11-L11 -> 0 | N11: =IF(F11="Promotional Incentive",0,I11) -> 1935 | O11: =IF(F11="Promotional Incentive",0,K11) -> 270.9 | P11: YES | Q11: JULIO RAMIREZ
A12: Progressive|875310026 | B12: Progressive | C12: Progressive Detailed Statement 06/2026 | D12: 875310026 | E12: RAMIREZ J. | F12: Credit Endorsement | G12: 06/16/2026 | H12: -244.71 | I12: -244.71 | J12: 0.14 | K12: -34.26 | L12: =ROUND(I12*J12,2) -> -34.26 | M12: =K12-L12 -> 0 | N12: =IF(F12="Promotional Incentive",0,I12) -> -244.71 | O12: =IF(F12="Promotional Incentive",0,K12) -> -34.26 | P12: YES | Q12: JULIO RAMIREZ
A13: Progressive|875520372 | B13: Progressive | C13: Progressive Detailed Statement 06/2026 | D13: 875520372 | E13: JONES J. | F13: New Business | G13: 06/12/2026 | H13: 4319 | I13: 4319 | J13: 0.1 | K13: 431.9 | L13: =ROUND(I13*J13,2) -> 431.9 | M13: =K13-L13 -> 0 | N13: =IF(F13="Promotional Incentive",0,I13) -> 4319 | O13: =IF(F13="Promotional Incentive",0,K13) -> 431.9 | P13: YES | Q13: JAMIE JONES
... A35: Progressive|999181480 | B35: Progressive | C35: Progressive Detailed Statement 06/2026 | D35: 999181480 | E35: PEREZ J. | F35: Renewal | G35: 06/21/2026 | H35: 619 | I35: 619 | J35: 0.1 | K35: 61.9 | L35: =ROUND(I35*J35,2) -> 61.9 | M35: =K35-L35 -> 0 | N35: =IF(F35="Promotional Incentive",0,I35) -> 619 | O35: =IF(F35="Promotional Incentive",0,K35) -> 61.9 | P35: YES | Q35: JUAN N PEREZ
A36: Progressive|1209267 | B36: Progressive | C36: Progressive Detailed Statement 06/2026 | D36: 01209267 | E36: EXPERT REMO . | F36: Endorsement | G36: 06/26/2026 | H36: 1717 | I36: 1717 | J36: 0.1 | K36: 171.7 | L36: =ROUND(I36*J36,2) -> 171.7 | M36: =K36-L36 -> 0 | N36: =IF(F36="Promotional Incentive",0,I36) -> 1717 | O36: =IF(F36="Promotional Incentive",0,K36) -> 171.7 | P36: No
A37: Progressive|862046493 | B37: Progressive | C37: Progressive Detailed Statement 06/2026 | D37: 862046493 | E37: BERMUDEZ V. | F37: Credit Endorsement | G37: 06/06/2026 | H37: -120.66 | I37: -120.66 | J37: 0.1 | K37: -12.07 | L37: =ROUND(I37*J37,2) -> -12.07 | M37: =K37-L37 -> 0 | N37: =IF(F37="Promotional Incentive",0,I37) -> -120.66 | O37: =IF(F37="Promotional Incentive",0,K37) -> -12.07 | P37: No
A38: Progressive|862085078 | B38: Progressive | C38: Progressive Detailed Statement 06/2026 | D38: 862085078 | E38: MOLINA LOZAN I. | F38: Endorsement | G38: 06/06/2026 | H38: 299.97 | I38: 299.97 | J38: 0.1 | K38: 30 | L38: =ROUND(I38*J38,2) -> 30 | M38: =K38-L38 -> 0 | N38: =IF(F38="Promotional Incentive",0,I38) -> 299.97 | O38: =IF(F38="Promotional Incentive",0,K38) -> 30 | P38: No
A39: Progressive|864173304 | B39: Progressive | C39: Progressive Detailed Statement 06/2026 | D39: 864173304 | E39: ATIAS O. | F39: Endorsement | G39: 06/07/2026 | H39: 213.57 | I39: 213.57 | J39: 0.1 | K39: 21.36 | L39: =ROUND(I39*J39,2) -> 21.36 | M39: =K39-L39 -> 0 | N39: =IF(F39="Promotional Incentive",0,I39) -> 213.57 | O39: =IF(F39="Promotional Incentive",0,K39) -> 21.36 | P39: No
A40: Progressive|866455034 | B40: Progressive | C40: Progressive Detailed Statement 06/2026 | D40: 866455034 | E40: BRAVO FLORES A. | F40: Renewal | G40: 06/16/2026 | H40: 1135 | I40: 1135 | J40: 0.1 | K40: 113.5 | L40: =ROUND(I40*J40,2) -> 113.5 | M40: =K40-L40 -> 0 | N40: =IF(F40="Promotional Incentive",0,I40) -> 1135 | O40: =IF(F40="Promotional Incentive",0,K40) -> 113.5 | P40: No
A41: Progressive|866544932 | B41: Progressive | C41: Progressive Detailed Statement 06/2026 | D41: 866544932 | E41: ZALDIVAR V. | F41: Renewal | G41: 06/18/2026 | H41: 1103 | I41: 1103 | J41: 0.1 | K41: 110.3 | L41: =ROUND(I41*J41,2) -> 110.3 | M41: =K41-L41 -> 0 | N41: =IF(F41="Promotional Incentive",0,I41) -> 1103 | O41: =IF(F41="Promotional Incentive",0,K41) -> 110.3 | P41: No
A42: Progressive|866921710 | B42: Progressive | C42: Progressive Detailed Statement 06/2026 | D42: 866921710 | E42: PEREZ H. | F42: Renewal | G42: 06/13/2026 | H42: 534 | I42: 534 | J42: 0.1 | K42: 53.4 | L42: =ROUND(I42*J42,2) -> 53.4 | M42: =K42-L42 -> 0 | N42: =IF(F42="Promotional Incentive",0,I42) -> 534 | O42: =IF(F42="Promotional Incentive",0,K42) -> 53.4 | P42: No
A43: Progressive|866944927 | B43: Progressive | C43: Progressive Detailed Statement 06/2026 | D43: 866944927 | E43: DA SILVA D. | F43: Renewal | G43: 06/14/2026 | H43: 1554 | I43: 1554 | J43: 0.1 | K43: 155.4 | L43: =ROUND(I43*J43,2) -> 155.4 | M43: =K43-L43 -> 0 | N43: =IF(F43="Promotional Incentive",0,I43) -> 1554 | O43: =IF(F43="Promotional Incentive",0,K43) -> 155.4 | P43: No
A44: Progressive|866989409 | B44: Progressive | C44: Progressive Detailed Statement 06/2026 | D44: 866989409 | E44: ACOBO M. | F44: Renewal | G44: 06/15/2026 | H44: 1486 | I44: 1486 | J44: 0.1 | K44: 148.6 | L44: =ROUND(I44*J44,2) -> 148.6 | M44: =K44-L44 -> 0 | N44: =IF(F44="Promotional Incentive",0,I44) -> 1486 | O44: =IF(F44="Promotional Incentive",0,K44) -> 148.6 | P44: No
A45: Progressive|867082146 | B45: Progressive | C45: Progressive Detailed Statement 06/2026 | D45: 867082146 | E45: RIVERA M. | F45: Endorsement | G45: 06/12/2026 | H45: 1.96 | I45: 1.96 | J45: 0.14 | K45: 0.27 | L45: =ROUND(I45*J45,2) -> 0.27 | M45: =K45-L45 -> 0 | N45: =IF(F45="Promotional Incentive",0,I45) -> 1.96 | O45: =IF(F45="Promotional Incentive",0,K45) -> 0.27 | P45: No
A46: Progressive|867301131 | B46: Progressive | C46: Progressive Detailed Statement 06/2026 | D46: 867301131 | E46: RICHARDS L. | F46: Renewal | G46: 06/23/2026 | H46: 476 | I46: 476 | J46: 0.1 | K46: 47.6 | L46: =ROUND(I46*J46,2) -> 47.6 | M46: =K46-L46 -> 0 | N46: =IF(F46="Promotional Incentive",0,I46) -> 476 | O46: =IF(F46="Promotional Incentive",0,K46) -> 47.6 | P46: No
A47: Progressive|867412033 | B47: Progressive | C47: Progressive Detailed Statement 06/2026 | D47: 867412033 | E47: GREEN K. | F47: Renewal | G47: 06/27/2026 | H47: 1473 | I47: 1473 | J47: 0.1 | K47: 147.3 | L47: =ROUND(I47*J47,2) -> 147.3 | M47: =K47-L47 -> 0 | N47: =IF(F47="Promotional Incentive",0,I47) -> 1473 | O47: =IF(F47="Promotional Incentive",0,K47) -> 147.3 | P47: No
... A189: Progressive|999745921 | B189: Progressive | C189: Progressive Detailed Statement 06/2026 | D189: 999745921 | E189: BLOMBERG E. | F189: Renewal | G189: 07/03/2026 | H189: 2048 | I189: 2048 | J189: 0.1 | K189: 204.8 | L189: =ROUND(I189*J189,2) -> 204.8 | M189: =K189-L189 -> 0 | N189: =IF(F189="Promotional Incentive",0,I189) -> 2048 | O189: =IF(F189="Promotional Incentive",0,K189) -> 204.8 | P189: No
A190: Infinity|10074082701 | B190: Infinity | C190: Kemper Auto Monthly Producer Stmt 06/2026 | D190: 10074082701 | E190: VERA, MANUEL | F190: Renewal | G190: 06/13/2026 | H190: 1425 | I190: 1425 | J190: 0.1 | K190: 142.5 | L190: =ROUND(I190*J190,2) -> 142.5 | M190: =K190-L190 -> 0 | N190: =IF(F190="Promotional Incentive",0,I190) -> 1425 | O190: =IF(F190="Promotional Incentive",0,K190) -> 142.5 | P190: YES | Q190: MANUEL VERA
A191: Infinity|10268755201 | B191: Infinity | C191: Kemper Auto Monthly Producer Stmt 06/2026 | D191: 10268755201 | E191: CASTILLO, MARLENE | F191: New | G191: 06/01/2026 | H191: 1183 | I191: 1183 | J191: 0.1 | K191: 118.3 | L191: =ROUND(I191*J191,2) -> 118.3 | M191: =K191-L191 -> 0 | N191: =IF(F191="Promotional Incentive",0,I191) -> 1183 | O191: =IF(F191="Promotional Incentive",0,K191) -> 118.3 | P191: YES | Q191: MARLENE CASTILLO
A192: Infinity|10268783901 | B192: Infinity | C192: Kemper Auto Monthly Producer Stmt 06/2026 | D192: 10268783901 | E192: JOHNSON, LIONEL | F192: New | G192: 06/05/2026 | H192: 934 | I192: 934 | J192: 0.1 | K192: 93.4 | L192: =ROUND(I192*J192,2) -> 93.4 | M192: =K192-L192 -> 0 | N192: =IF(F192="Promotional Incentive",0,I192) -> 934 | O192: =IF(F192="Promotional Incentive",0,K192) -> 93.4 | P192: YES | Q192: LIONEL JOHNSON
A193: Infinity|10270293001 | B193: Infinity | C193: Kemper Auto Monthly Producer Stmt 06/2026 | D193: 10270293001 | E193: PRESSLEY, TAURUS | F193: New | G193: 06/20/2026 | H193: 810 | I193: 810 | J193: 0.1 | K193: 81 | L193: =ROUND(I193*J193,2) -> 81 | M193: =K193-L193 -> 0 | N193: =IF(F193="Promotional Incentive",0,I193) -> 810 | O193: =IF(F193="Promotional Incentive",0,K193) -> 81 | P193: YES | Q193: TAURUS L. PRESSLEY
A194: Infinity|10270429601 | B194: Infinity | C194: Kemper Auto Monthly Producer Stmt 06/2026 | D194: 10270429601 | E194: GONZALEZ, FELIPE | F194: New | G194: 06/23/2026 | H194: 1450 | I194: 1450 | J194: 0.1 | K194: 145 | L194: =ROUND(I194*J194,2) -> 145 | M194: =K194-L194 -> 0 | N194: =IF(F194="Promotional Incentive",0,I194) -> 1450 | O194: =IF(F194="Promotional Incentive",0,K194) -> 145 | P194: YES | Q194: FELIPE GONZALEZ
A195: Infinity|10027857401 | B195: Infinity | C195: Kemper Auto Monthly Producer Stmt 06/2026 | D195: 10027857401 | E195: VALDES, VICTOR | F195: ENDORSE | G195: 06/08/2026 | H195: 36 | I195: 36 | J195: 0.1 | K195: 3.6 | L195: =ROUND(I195*J195,2) -> 3.6 | M195: =K195-L195 -> 0 | N195: =IF(F195="Promotional Incentive",0,I195) -> 36 | O195: =IF(F195="Promotional Incentive",0,K195) -> 3.6 | P195: No
A196: Infinity|10027857401 | B196: Infinity | C196: Kemper Auto Monthly Producer Stmt 06/2026 | D196: 10027857401 | E196: VALDES, VICTOR | F196: CnxFinal | G196: 06/26/2026 | H196: -189 | I196: -189 | J196: 0.1 | K196: -18.9 | L196: =ROUND(I196*J196,2) -> -18.9 | M196: =K196-L196 -> 0 | N196: =IF(F196="Promotional Incentive",0,I196) -> -189 | O196: =IF(F196="Promotional Incentive",0,K196) -> -18.9 | P196: No
A197: Infinity|10193915602 | B197: Infinity | C197: Kemper Auto Monthly Producer Stmt 06/2026 | D197: 10193915602 | E197: TAS, RESUL | F197: New | G197: 06/17/2026 | H197: 361 | I197: 361 | J197: 0.1 | K197: 36.1 | L197: =ROUND(I197*J197,2) -> 36.1 | M197: =K197-L197 -> 0 | N197: =IF(F197="Promotional Incentive",0,I197) -> 361 | O197: =IF(F197="Promotional Incentive",0,K197) -> 36.1 | P197: No
A198: Infinity|10213255201 | B198: Infinity | C198: Kemper Auto Monthly Producer Stmt 06/2026 | D198: 10213255201 | E198: PEREZ ROY, JUAN | F198: CnxFinal | G198: 05/23/2026 | H198: -584 | I198: -584 | J198: 0.1 | K198: -58.4 | L198: =ROUND(I198*J198,2) -> -58.4 | M198: =K198-L198 -> 0 | N198: =IF(F198="Promotional Incentive",0,I198) -> -584 | O198: =IF(F198="Promotional Incentive",0,K198) -> -58.4 | P198: No
A199: Infinity|10213255201 | B199: Infinity | C199: Kemper Auto Monthly Producer Stmt 06/2026 | D199: 10213255201 | E199: PEREZ ROY, JUAN | F199: CnxFinal | G199: 06/29/2026 | H199: -2950 | I199: -2950 | J199: 0.1 | K199: -295 | L199: =ROUND(I199*J199,2) -> -295 | M199: =K199-L199 -> 0 | N199: =IF(F199="Promotional Incentive",0,I199) -> -2950 | O199: =IF(F199="Promotional Incentive",0,K199) -> -295 | P199: No
A200: Infinity|10239866201 | B200: Infinity | C200: Kemper Auto Monthly Producer Stmt 06/2026 | D200: 10239866201 | E200: FRATER, SYLVESTER | F200: CnxFinal | G200: 06/14/2026 | H200: -460 | I200: -460 | J200: 0.1 | K200: -46 | L200: =ROUND(I200*J200,2) -> -46 | M200: =K200-L200 -> 0 | N200: =IF(F200="Promotional Incentive",0,I200) -> -460 | O200: =IF(F200="Promotional Incentive",0,K200) -> -46 | P200: No
A201: Infinity|10260538001 | B201: Infinity | C201: Kemper Auto Monthly Producer Stmt 06/2026 | D201: 10260538001 | E201: RAI, DIVYANI | F201: ENDORSE | G201: 06/20/2026 | H201: -6 | I201: -6 | J201: 0.1 | K201: -0.6 | L201: =ROUND(I201*J201,2) -> -0.6 | M201: =K201-L201 -> 0 | N201: =IF(F201="Promotional Incentive",0,I201) -> -6 | O201: =IF(F201="Promotional Incentive",0,K201) -> -0.6 | P201: No
A202: Infinity|10260538001 | B202: Infinity | C202: Kemper Auto Monthly Producer Stmt 06/2026 | D202: 10260538001 | E202: RAI, DIVYANI | F202: ENDORSE | G202: 06/20/2026 | H202: -44 | I202: -44 | J202: 0.1 | K202: -4.4 | L202: =ROUND(I202*J202,2) -> -4.4 | M202: =K202-L202 -> 0 | N202: =IF(F202="Promotional Incentive",0,I202) -> -44 | O202: =IF(F202="Promotional Incentive",0,K202) -> -4.4 | P202: No
A203: Infinity|10260713001 | B203: Infinity | C203: Kemper Auto Monthly Producer Stmt 06/2026 | D203: 10260713001 | E203: MENDOZA, JABIERQUIS | F203: CnxFinal | G203: 06/03/2026 | H203: -698 | I203: -698 | J203: 0.1 | K203: -69.8 | L203: =ROUND(I203*J203,2) -> -69.8 | M203: =K203-L203 -> 0 | N203: =IF(F203="Promotional Incentive",0,I203) -> -698 | O203: =IF(F203="Promotional Incentive",0,K203) -> -69.8 | P203: No
A204: Infinity|10269872401 | B204: Infinity | C204: Kemper Auto Monthly Producer Stmt 06/2026 | D204: 10269872401 | E204: Douek, Hadass | F204: New | G204: 06/15/2026 | H204: 1653 | I204: 1653 | J204: 0.1 | K204: 165.3 | L204: =ROUND(I204*J204,2) -> 165.3 | M204: =K204-L204 -> 0 | N204: =IF(F204="Promotional Incentive",0,I204) -> 1653 | O204: =IF(F204="Promotional Incentive",0,K204) -> 165.3 | P204: No
A205: Infinity|10269872401 | B205: Infinity | C205: Kemper Auto Monthly Producer Stmt 06/2026 | D205: 10269872401 | E205: Douek, Hadass | F205: ENDORSE | G205: 06/15/2026 | H205: 170 | I205: 170 | J205: 0.1 | K205: 17 | L205: =ROUND(I205*J205,2) -> 17 | M205: =K205-L205 -> 0 | N205: =IF(F205="Promotional Incentive",0,I205) -> 170 | O205: =IF(F205="Promotional Incentive",0,K205) -> 17 | P205: No
A206: Infinity|10269872401 | B206: Infinity | C206: Kemper Auto Monthly Producer Stmt 06/2026 | D206: 10269872401 | E206: Douek, Hadass | F206: ENDORSE | G206: 06/26/2026 | H206: -160 | I206: -160 | J206: 0.1 | K206: -16 | L206: =ROUND(I206*J206,2) -> -16 | M206: =K206-L206 -> 0 | N206: =IF(F206="Promotional Incentive",0,I206) -> -160 | O206: =IF(F206="Promotional Incentive",0,K206) -> -16 | P206: No
... A216: Infinity|50030429301 | B216: Infinity | C216: Kemper Auto Monthly Producer Stmt 06/2026 | D216: 50030429301 | E216: Almonte, Manuela | F216: ENDORSE | G216: 06/05/2026 | H216: 84 | I216: 84 | J216: 0.1 | K216: 8.4 | L216: =ROUND(I216*J216,2) -> 8.4 | M216: =K216-L216 -> 0 | N216: =IF(F216="Promotional Incentive",0,I216) -> 84 | O216: =IF(F216="Promotional Incentive",0,K216) -> 8.4 | P216: No
A217: United Auto|UAD605735805 | B217: United Auto | C217: United Insurance Group Direct Billing Stmt 06/2026 | D217: UAD 605735805 | E217: SANDRA ZAMBRANA | F217: Comm as Collected | G217: 06/30/26 | H217: 221.6 | I217: 221.6 | J217: 0.1 | K217: 22.16 | L217: =ROUND(I217*J217,2) -> 22.16 | M217: =K217-L217 -> 0 | N217: =IF(F217="Promotional Incentive",0,I217) -> 221.6 | O217: =IF(F217="Promotional Incentive",0,K217) -> 22.16 | P217: YES | Q217: SANDRA ZAMBRANA
A218: United Auto|UAD605735805 | B218: United Auto | C218: United Insurance Group Direct Billing Stmt 06/2026 | D218: UAD 605735805 | E218: SANDRA ZAMBRANA | F218: Promotional Incentive | G218: 06/30/26 | H218: 221.6 | I218: 221.6 | J218: 0.03 | K218: 6.64 | L218: =ROUND(I218*J218,2) -> 6.65 | M218: =K218-L218 -> -0.01 | N218: =IF(F218="Promotional Incentive",0,I218) -> 0 | O218: =IF(F218="Promotional Incentive",0,K218) -> 0 | P218: YES | Q218: SANDRA ZAMBRANA
A219: United Auto|UAE20965001 | B219: United Auto | C219: United Insurance Group Direct Billing Stmt 06/2026 | D219: UAE 020965001 | E219: HECTOR L RODRIGUEZ RA | F219: Comm as Collected | G219: 06/30/26 | H219: 147.7 | I219: 147.7 | J219: 0.1 | K219: 14.77 | L219: =ROUND(I219*J219,2) -> 14.77 | M219: =K219-L219 -> 0 | N219: =IF(F219="Promotional Incentive",0,I219) -> 147.7 | O219: =IF(F219="Promotional Incentive",0,K219) -> 14.77 | P219: YES | Q219: HECTOR LUIS RODRIGUEZ RAMOS
A220: United Auto|UAE20965001 | B220: United Auto | C220: United Insurance Group Direct Billing Stmt 06/2026 | D220: UAE 020965001 | E220: HECTOR L RODRIGUEZ RA | F220: Promotional Incentive | G220: 06/30/26 | H220: 147.7 | I220: 147.7 | J220: 0.03 | K220: 4.43 | L220: =ROUND(I220*J220,2) -> 4.43 | M220: =K220-L220 -> 0 | N220: =IF(F220="Promotional Incentive",0,I220) -> 0 | O220: =IF(F220="Promotional Incentive",0,K220) -> 0 | P220: YES | Q220: HECTOR LUIS RODRIGUEZ RAMOS
A221: United Auto|UAO653831 | B221: United Auto | C221: United Insurance Group Direct Billing Stmt 06/2026 | D221: UAO 000653831 | E221: YAINELYS DIAZ SALAZAR | F221: Comm as Collected | G221: 06/30/26 | H221: 236.7 | I221: 236.7 | J221: 0.1 | K221: 23.67 | L221: =ROUND(I221*J221,2) -> 23.67 | M221: =K221-L221 -> 0 | N221: =IF(F221="Promotional Incentive",0,I221) -> 236.7 | O221: =IF(F221="Promotional Incentive",0,K221) -> 23.67 | P221: YES | Q221: YAINELYS DIAZ SALAZAR
A222: United Auto|UAO653867 | B222: United Auto | C222: United Insurance Group Direct Billing Stmt 06/2026 | D222: UAO 000653867 | E222: CHRISTIAN O CARBOT | F222: Comm as Collected | G222: 06/30/26 | H222: 359.7 | I222: 359.7 | J222: 0.1 | K222: 35.97 | L222: =ROUND(I222*J222,2) -> 35.97 | M222: =K222-L222 -> 0 | N222: =IF(F222="Promotional Incentive",0,I222) -> 359.7 | O222: =IF(F222="Promotional Incentive",0,K222) -> 35.97 | P222: YES | Q222: CHRISTIAN O. CARBOT
A223: United Auto|UAO692181 | B223: United Auto | C223: United Insurance Group Direct Billing Stmt 06/2026 | D223: UAO 000692181 | E223: LUIS A ORTIZ | F223: Comm as Collected | G223: 06/30/26 | H223: 163.6 | I223: 163.6 | J223: 0.1 | K223: 16.36 | L223: =ROUND(I223*J223,2) -> 16.36 | M223: =K223-L223 -> 0 | N223: =IF(F223="Promotional Incentive",0,I223) -> 163.6 | O223: =IF(F223="Promotional Incentive",0,K223) -> 16.36 | P223: YES | Q223: LUIS A. ORTIZ
A224: United Auto|UAO692181 | B224: United Auto | C224: United Insurance Group Direct Billing Stmt 06/2026 | D224: UAO 000692181 | E224: LUIS A ORTIZ | F224: Promotional Incentive | G224: 06/30/26 | H224: 163.6 | I224: 163.6 | J224: 0.03 | K224: 4.9 | L224: =ROUND(I224*J224,2) -> 4.91 | M224: =K224-L224 -> -0.01 | N224: =IF(F224="Promotional Incentive",0,I224) -> 0 | O224: =IF(F224="Promotional Incentive",0,K224) -> 0 | P224: YES | Q224: LUIS A. ORTIZ
A225: United Auto|UAO694805 | B225: United Auto | C225: United Insurance Group Direct Billing Stmt 06/2026 | D225: UAO 000694805 | E225: JEAN H GUSTAVE | F225: New Business | G225: 06/13/26 | H225: 2797 | I225: 2797 | J225: 0.1 | K225: 279.7 | L225: =ROUND(I225*J225,2) -> 279.7 | M225: =K225-L225 -> 0 | N225: =IF(F225="Promotional Incentive",0,I225) -> 2797 | O225: =IF(F225="Promotional Incentive",0,K225) -> 279.7 | P225: YES | Q225: JEAN H. GUSTAVE
A226: United Auto|UAO694805 | B226: United Auto | C226: United Insurance Group Direct Billing Stmt 06/2026 | D226: UAO 000694805 | E226: JEAN H GUSTAVE | F226: Promotional Incentive | G226: 06/13/26 | H226: 2797 | I226: 2797 | J226: 0.03 | K226: 83.91 | L226: =ROUND(I226*J226,2) -> 83.91 | M226: =K226-L226 -> 0 | N226: =IF(F226="Promotional Incentive",0,I226) -> 0 | O226: =IF(F226="Promotional Incentive",0,K226) -> 0 | P226: YES | Q226: JEAN H. GUSTAVE
A227: United Auto|UAO695126 | B227: United Auto | C227: United Insurance Group Direct Billing Stmt 06/2026 | D227: UAO 000695126 | E227: YADIER CORDERO GOVEA | F227: New Business | G227: 06/15/26 | H227: 2233 | I227: 2233 | J227: 0.1 | K227: 223.3 | L227: =ROUND(I227*J227,2) -> 223.3 | M227: =K227-L227 -> 0 | N227: =IF(F227="Promotional Incentive",0,I227) -> 2233 | O227: =IF(F227="Promotional Incentive",0,K227) -> 223.3 | P227: YES | Q227: YADIER CORDERO G.
A228: United Auto|UAO695126 | B228: United Auto | C228: United Insurance Group Direct Billing Stmt 06/2026 | D228: UAO 000695126 | E228: YADIER CORDERO GOVEA | F228: Promotional Incentive | G228: 06/15/26 | H228: 2233 | I228: 2233 | J228: 0.03 | K228: 66.99 | L228: =ROUND(I228*J228,2) -> 66.99 | M228: =K228-L228 -> 0 | N228: =IF(F228="Promotional Incentive",0,I228) -> 0 | O228: =IF(F228="Promotional Incentive",0,K228) -> 0 | P228: YES | Q228: YADIER CORDERO G.
... A236: United Auto|UAO44288703 | B236: United Auto | C236: United Insurance Group Direct Billing Stmt 06/2026 | D236: UAO 044288703 | E236: TAMEKA L GREENE FOOTM | F236: Promotional Incentive | G236: 06/30/26 | H236: 162 | I236: 162 | J236: 0.03 | K236: 4.86 | L236: =ROUND(I236*J236,2) -> 4.86 | M236: =K236-L236 -> 0 | N236: =IF(F236="Promotional Incentive",0,I236) -> 0 | O236: =IF(F236="Promotional Incentive",0,K236) -> 0 | P236: YES | Q236: TAMEKA GREENE
A237: United Auto|UAD602082206 | B237: United Auto | C237: United Insurance Group Direct Billing Stmt 06/2026 | D237: UAD 602082206 | E237: VICTOR E GARCIA BARRE | F237: Comm as Collected | G237: 06/30/26 | H237: 269.1 | I237: 269.1 | J237: 0.1 | K237: 26.91 | L237: =ROUND(I237*J237,2) -> 26.91 | M237: =K237-L237 -> 0 | N237: =IF(F237="Promotional Incentive",0,I237) -> 269.1 | O237: =IF(F237="Promotional Incentive",0,K237) -> 26.91 | P237: No
A238: United Auto|UAD604178202 | B238: United Auto | C238: United Insurance Group Direct Billing Stmt 06/2026 | D238: UAD 604178202 | E238: OLKYS BORGES GARCIA | F238: Comm as Collected | G238: 06/30/26 | H238: 137.6 | I238: 137.6 | J238: 0.1 | K238: 13.76 | L238: =ROUND(I238*J238,2) -> 13.76 | M238: =K238-L238 -> 0 | N238: =IF(F238="Promotional Incentive",0,I238) -> 137.6 | O238: =IF(F238="Promotional Incentive",0,K238) -> 13.76 | P238: No
A239: United Auto|UAD606159902 | B239: United Auto | C239: United Insurance Group Direct Billing Stmt 06/2026 | D239: UAD 606159902 | E239: TIMMIE ROZIER | F239: Comm as Collected | G239: 06/30/26 | H239: 178.9 | I239: 178.9 | J239: 0.1 | K239: 17.89 | L239: =ROUND(I239*J239,2) -> 17.89 | M239: =K239-L239 -> 0 | N239: =IF(F239="Promotional Incentive",0,I239) -> 178.9 | O239: =IF(F239="Promotional Incentive",0,K239) -> 17.89 | P239: No
A240: United Auto|UAD606715305 | B240: United Auto | C240: United Insurance Group Direct Billing Stmt 06/2026 | D240: UAD 606715305 | E240: BIANCA R BUZZIZ | F240: Comm as Collected | G240: 06/30/26 | H240: 212.9 | I240: 212.9 | J240: 0.1 | K240: 21.29 | L240: =ROUND(I240*J240,2) -> 21.29 | M240: =K240-L240 -> 0 | N240: =IF(F240="Promotional Incentive",0,I240) -> 212.9 | O240: =IF(F240="Promotional Incentive",0,K240) -> 21.29 | P240: No
A241: United Auto|UAD607888404 | B241: United Auto | C241: United Insurance Group Direct Billing Stmt 06/2026 | D241: UAD 607888404 | E241: ORESTE CANIZARES GONZ | F241: Comm as Collected | G241: 06/30/26 | H241: 202.2 | I241: 202.2 | J241: 0.1 | K241: 20.22 | L241: =ROUND(I241*J241,2) -> 20.22 | M241: =K241-L241 -> 0 | N241: =IF(F241="Promotional Incentive",0,I241) -> 202.2 | O241: =IF(F241="Promotional Incentive",0,K241) -> 20.22 | P241: No
A242: United Auto|UAD607888404 | B242: United Auto | C242: United Insurance Group Direct Billing Stmt 06/2026 | D242: UAD 607888404 | E242: ORESTE CANIZARES GONZ | F242: Promotional Incentive | G242: 06/30/26 | H242: 202.2 | I242: 202.2 | J242: 0.03 | K242: 6.06 | L242: =ROUND(I242*J242,2) -> 6.07 | M242: =K242-L242 -> -0.01 | N242: =IF(F242="Promotional Incentive",0,I242) -> 0 | O242: =IF(F242="Promotional Incentive",0,K242) -> 0 | P242: No
A243: United Auto|UAD609746902 | B243: United Auto | C243: United Insurance Group Direct Billing Stmt 06/2026 | D243: UAD 609746902 | E243: YUSMANY CARDOSO ROJAS | F243: Comm as Collected | G243: 06/30/26 | H243: 138.1 | I243: 138.1 | J243: 0.1 | K243: 13.81 | L243: =ROUND(I243*J243,2) -> 13.81 | M243: =K243-L243 -> 0 | N243: =IF(F243="Promotional Incentive",0,I243) -> 138.1 | O243: =IF(F243="Promotional Incentive",0,K243) -> 13.81 | P243: No
A244: United Auto|UAD610261501 | B244: United Auto | C244: United Insurance Group Direct Billing Stmt 06/2026 | D244: UAD 610261501 | E244: DALICIA MOLINA SERRAN | F244: Comm as Collected | G244: 06/30/26 | H244: 75.6 | I244: 75.6 | J244: 0.1 | K244: 7.56 | L244: =ROUND(I244*J244,2) -> 7.56 | M244: =K244-L244 -> 0 | N244: =IF(F244="Promotional Incentive",0,I244) -> 75.6 | O244: =IF(F244="Promotional Incentive",0,K244) -> 7.56 | P244: No
A245: United Auto|UAD610261501 | B245: United Auto | C245: United Insurance Group Direct Billing Stmt 06/2026 | D245: UAD 610261501 | E245: DALICIA MOLINA SERRAN | F245: Promotional Incentive | G245: 06/30/26 | H245: 75.6 | I245: 75.6 | J245: 0.03 | K245: 2.26 | L245: =ROUND(I245*J245,2) -> 2.27 | M245: =K245-L245 -> -0.01 | N245: =IF(F245="Promotional Incentive",0,I245) -> 0 | O245: =IF(F245="Promotional Incentive",0,K245) -> 0 | P245: No
A246: United Auto|UAE217449 | B246: United Auto | C246: United Insurance Group Direct Billing Stmt 06/2026 | D246: UAE 000217449 | E246: JOSE A CRUZ PEREZ | F246: Comm as Collected | G246: 06/30/26 | H246: 420.7 | I246: 420.7 | J246: 0.1 | K246: 42.07 | L246: =ROUND(I246*J246,2) -> 42.07 | M246: =K246-L246 -> 0 | N246: =IF(F246="Promotional Incentive",0,I246) -> 420.7 | O246: =IF(F246="Promotional Incentive",0,K246) -> 42.07 | P246: No
A247: United Auto|UAE223913 | B247: United Auto | C247: United Insurance Group Direct Billing Stmt 06/2026 | D247: UAE 000223913 | E247: CODY J MCINTYRE | F247: Comm as Collected | G247: 06/30/26 | H247: 158.9 | I247: 158.9 | J247: 0.1 | K247: 15.89 | L247: =ROUND(I247*J247,2) -> 15.89 | M247: =K247-L247 -> 0 | N247: =IF(F247="Promotional Incentive",0,I247) -> 158.9 | O247: =IF(F247="Promotional Incentive",0,K247) -> 15.89 | P247: No
A248: United Auto|UAE225427 | B248: United Auto | C248: United Insurance Group Direct Billing Stmt 06/2026 | D248: UAE 000225427 | E248: JUAN J PAYANO | F248: Comm as Collected | G248: 06/30/26 | H248: 190.6 | I248: 190.6 | J248: 0.1 | K248: 19.06 | L248: =ROUND(I248*J248,2) -> 19.06 | M248: =K248-L248 -> 0 | N248: =IF(F248="Promotional Incentive",0,I248) -> 190.6 | O248: =IF(F248="Promotional Incentive",0,K248) -> 19.06 | P248: No
... A314: United Auto|UAO64893001 | B314: United Auto | C314: United Insurance Group Direct Billing Stmt 06/2026 | D314: UAO 064893001 | E314: LUIS VICENT | F314: Promotional Incentive | G314: 06/30/26 | H314: 135.3 | I314: 135.3 | J314: 0.03 | K314: 4.05 | L314: =ROUND(I314*J314,2) -> 4.06 | M314: =K314-L314 -> -0.01 | N314: =IF(F314="Promotional Incentive",0,I314) -> 0 | O314: =IF(F314="Promotional Incentive",0,K314) -> 0 | P314: No
A315: Ocean Harbor|P20082297007 | B315: Ocean Harbor | C315: Pearl Holding Group Commission Stmt 06/2026 | D315: P020082297007 | E315: FORERO AVENDANO, JAVIER A | F315: Renewal | G315: 06/05/2026 | H315: 1188 | I315: 1153 | J315: 0.11 | K315: 126.83 | L315: =ROUND(I315*J315,2) -> 126.83 | M315: =K315-L315 -> 0 | N315: =IF(F315="Promotional Incentive",0,I315) -> 1153 | O315: =IF(F315="Promotional Incentive",0,K315) -> 126.83 | P315: YES | Q315: JAVIER FORERO
A316: Ocean Harbor|P20082739007 | B316: Ocean Harbor | C316: Pearl Holding Group Commission Stmt 06/2026 | D316: P020082739007 | E316: JUNCO JIMENEZ, YUSDELY | F316: Renewal | G316: 06/14/2026 | H316: 1176 | I316: 1141 | J316: 0.11 | K316: 125.51 | L316: =ROUND(I316*J316,2) -> 125.51 | M316: =K316-L316 -> 0 | N316: =IF(F316="Promotional Incentive",0,I316) -> 1141 | O316: =IF(F316="Promotional Incentive",0,K316) -> 125.51 | P316: YES | Q316: YUSDELY JUNCO
A317: Ocean Harbor|P20061781209 | B317: Ocean Harbor | C317: Pearl Holding Group Commission Stmt 06/2026 | D317: P020061781209 | E317: CASTRO, LESLY T | F317: Cancellation | G317: 05/15/2026 | H317: -555 | I317: -555 | J317: 0.11 | K317: -61.05 | L317: =ROUND(I317*J317,2) -> -61.05 | M317: =K317-L317 -> 0 | N317: =IF(F317="Promotional Incentive",0,I317) -> -555 | O317: =IF(F317="Promotional Incentive",0,K317) -> -61.05 | P317: No
A318: Ocean Harbor|P20063965109 | B318: Ocean Harbor | C318: Pearl Holding Group Commission Stmt 06/2026 | D318: P020063965109 | E318: ABREU, DARIO | F318: Renewal | G318: 06/10/2026 | H318: 1808 | I318: 1773 | J318: 0.11 | K318: 195.03 | L318: =ROUND(I318*J318,2) -> 195.03 | M318: =K318-L318 -> 0 | N318: =IF(F318="Promotional Incentive",0,I318) -> 1773 | O318: =IF(F318="Promotional Incentive",0,K318) -> 195.03 | P318: No
A319: Ocean Harbor|P20109544801 | B319: Ocean Harbor | C319: Pearl Holding Group Commission Stmt 06/2026 | D319: P020109544801 | E319: JOHNSON, JAHMAR J | F319: Cancellation | G319: 06/01/2026 | H319: -434 | I319: -434 | J319: 0.13 | K319: -56.42 | L319: =ROUND(I319*J319,2) -> -56.42 | M319: =K319-L319 -> 0 | N319: =IF(F319="Promotional Incentive",0,I319) -> -434 | O319: =IF(F319="Promotional Incentive",0,K319) -> -56.42 | P319: No
A320: Ocean Harbor|P20109544801 | B320: Ocean Harbor | C320: Pearl Holding Group Commission Stmt 06/2026 | D320: P020109544801 | E320: JOHNSON, JAHMAR J | F320: Uncollected Premium | G320: 06/01/2026 | H320: -28.42 | I320: -28.42 | J320: 0.13 | K320: -3.69 | L320: =ROUND(I320*J320,2) -> -3.69 | M320: =K320-L320 -> 0 | N320: =IF(F320="Promotional Incentive",0,I320) -> -28.42 | O320: =IF(F320="Promotional Incentive",0,K320) -> -3.69 | P320: No
A321: National General|202333293604 | B321: National General | C321: National General Commission Stmt 06/2026 | D321: 2023332936 04 | E321: Eduardo Gomes | F321: Renew | G321: 6/1/2026 | H321: 401 | I321: 401 | J321: 0.1 | K321: 40.1 | L321: =ROUND(I321*J321,2) -> 40.1 | M321: =K321-L321 -> 0 | N321: =IF(F321="Promotional Incentive",0,I321) -> 401 | O321: =IF(F321="Promotional Incentive",0,K321) -> 40.1 | P321: YES | Q321: EDUARDO GOMES
A322: National General|202333293604 | B322: National General | C322: National General Commission Stmt 06/2026 | D322: 2023332936 04 | E322: Eduardo Gomes | F322: Endorsement | G322: 6/1/2026 | H322: 650 | I322: 650 | J322: 0.1 | K322: 65 | L322: =ROUND(I322*J322,2) -> 65 | M322: =K322-L322 -> 0 | N322: =IF(F322="Promotional Incentive",0,I322) -> 650 | O322: =IF(F322="Promotional Incentive",0,K322) -> 65 | P322: YES | Q322: EDUARDO GOMES
A323: National General|202333293604 | B323: National General | C323: National General Commission Stmt 06/2026 | D323: 2023332936 04 | E323: Eduardo Gomes | F323: Endorsement | G323: 6/18/2026 | H323: -132 | I323: -132 | J323: 0.1 | K323: -13.2 | L323: =ROUND(I323*J323,2) -> -13.2 | M323: =K323-L323 -> 0 | N323: =IF(F323="Promotional Incentive",0,I323) -> -132 | O323: =IF(F323="Promotional Incentive",0,K323) -> -13.2 | P323: YES | Q323: EDUARDO GOMES
A324: National General|202352077004 | B324: National General | C324: National General Commission Stmt 06/2026 | D324: 2023520770 04 | E324: Eiglys Hernandez | F324: Renew | G324: 6/13/2026 | H324: 1415 | I324: 1415 | J324: 0.1 | K324: 141.5 | L324: =ROUND(I324*J324,2) -> 141.5 | M324: =K324-L324 -> 0 | N324: =IF(F324="Promotional Incentive",0,I324) -> 1415 | O324: =IF(F324="Promotional Incentive",0,K324) -> 141.5 | P324: YES | Q324: EIGLYS M HERNANDEZ
A325: National General|201902999606 | B325: National General | C325: National General Commission Stmt 06/2026 | D325: 2019029996 06 | E325: Ignacio Mora | F325: Renew | G325: 6/24/2026 | H325: 999 | I325: 999 | J325: 0.1 | K325: 99.9 | L325: =ROUND(I325*J325,2) -> 99.9 | M325: =K325-L325 -> 0 | N325: =IF(F325="Promotional Incentive",0,I325) -> 999 | O325: =IF(F325="Promotional Incentive",0,K325) -> 99.9 | P325: No
A326: National General|202127680505 | B326: National General | C326: National General Commission Stmt 06/2026 | D326: 2021276805 05 | E326: Sagar Chavan | F326: Renew | G326: 6/30/2026 | H326: 869 | I326: 869 | J326: 0.1 | K326: 86.9 | L326: =ROUND(I326*J326,2) -> 86.9 | M326: =K326-L326 -> 0 | N326: =IF(F326="Promotional Incentive",0,I326) -> 869 | O326: =IF(F326="Promotional Incentive",0,K326) -> 86.9 | P326: No
A327: National General|202184329804 | B327: National General | C327: National General Commission Stmt 06/2026 | D327: 2021843298 04 | E327: Evicson Crespo | F327: Endorsement | G327: 6/6/2026 | H327: -42 | I327: -42 | J327: 0.1 | K327: -4.2 | L327: =ROUND(I327*J327,2) -> -4.2 | M327: =K327-L327 -> 0 | N327: =IF(F327="Promotional Incentive",0,I327) -> -42 | O327: =IF(F327="Promotional Incentive",0,K327) -> -4.2 | P327: No
A328: National General|202237548104 | B328: National General | C328: National General Commission Stmt 06/2026 | D328: 2022375481 04 | E328: Makiyah Moore | F328: Endorsement | G328: 6/23/2026 | H328: 69 | I328: 69 | J328: 0.1 | K328: 6.9 | L328: =ROUND(I328*J328,2) -> 6.9 | M328: =K328-L328 -> 0 | N328: =IF(F328="Promotional Incentive",0,I328) -> 69 | O328: =IF(F328="Promotional Incentive",0,K328) -> 6.9 | P328: No
A329: National General|202327682902 | B329: National General | C329: National General Commission Stmt 06/2026 | D329: 2023276829 02 | E329: Jorge Pacheco Ruiz | F329: Renew | G329: 6/1/2026 | H329: 2103 | I329: 2103 | J329: 0.1 | K329: 210.3 | L329: =ROUND(I329*J329,2) -> 210.3 | M329: =K329-L329 -> 0 | N329: =IF(F329="Promotional Incentive",0,I329) -> 2103 | O329: =IF(F329="Promotional Incentive",0,K329) -> 210.3 | P329: No
A330: National General|202349536604 | B330: National General | C330: National General Commission Stmt 06/2026 | D330: 2023495366 04 | E330: Lisa Gori | F330: Renew | G330: 6/12/2026 | H330: 1931 | I330: 1931 | J330: 0.1 | K330: 193.1 | L330: =ROUND(I330*J330,2) -> 193.1 | M330: =K330-L330 -> 0 | N330: =IF(F330="Promotional Incentive",0,I330) -> 1931 | O330: =IF(F330="Promotional Incentive",0,K330) -> 193.1 | P330: No
A331: National General|202470423402 | B331: National General | C331: National General Commission Stmt 06/2026 | D331: 2024704234 02 | E331: Erglyn Zambrano | F331: Uncollected Premium | G331: 2/17/2026 | H331: -57.3 | I331: -57.3 | J331: 0.1 | K331: -5.73 | L331: =ROUND(I331*J331,2) -> -5.73 | M331: =K331-L331 -> 0 | N331: =IF(F331="Promotional Incentive",0,I331) -> -57.3 | O331: =IF(F331="Promotional Incentive",0,K331) -> -5.73 | P331: No
A332: National General|203116217101 | B332: National General | C332: National General Commission Stmt 06/2026 | D332: 2031162171 01 | E332: Dayana Canova | F332: Endorsement | G332: 6/15/2026 | H332: 4 | I332: 4 | J332: 0.1 | K332: 0.4 | L332: =ROUND(I332*J332,2) -> 0.4 | M332: =K332-L332 -> 0 | N332: =IF(F332="Promotional Incentive",0,I332) -> 4 | O332: =IF(F332="Promotional Incentive",0,K332) -> 0.4 | P332: No
A333: National General|203213292401 | B333: National General | C333: National General Commission Stmt 06/2026 | D333: 2032132924 01 | E333: Sindy Molina | F333: Cancel | G333: 6/23/2026 | H333: -791 | I333: -791 | J333: 0.1 | K333: -79.1 | L333: =ROUND(I333*J333,2) -> -79.1 | M333: =K333-L333 -> 0 | N333: =IF(F333="Promotional Incentive",0,I333) -> -791 | O333: =IF(F333="Promotional Incentive",0,K333) -> -79.1 | P333: No
A334: National General|203321124200 | B334: National General | C334: National General Commission Stmt 06/2026 | D334: 2033211242 00 | E334: Kevin Jimenez Aguero | F334: Endorsement | G334: 6/2/2026 | H334: 312 | I334: 312 | J334: 0.1 | K334: 31.2 | L334: =ROUND(I334*J334,2) -> 31.2 | M334: =K334-L334 -> 0 | N334: =IF(F334="Promotional Incentive",0,I334) -> 312 | O334: =IF(F334="Promotional Incentive",0,K334) -> 31.2 | P334: No
A335: National General|203364914000 | B335: National General | C335: National General Commission Stmt 06/2026 | D335: 2033649140 00 | E335: Deamonte Maree | F335: Endorsement | G335: 6/18/2026 | H335: 44 | I335: 44 | J335: 0.1 | K335: 4.4 | L335: =ROUND(I335*J335,2) -> 4.4 | M335: =K335-L335 -> 0 | N335: =IF(F335="Promotional Incentive",0,I335) -> 44 | O335: =IF(F335="Promotional Incentive",0,K335) -> 4.4 | P335: No
A336: National General|203364914000 | B336: National General | C336: National General Commission Stmt 06/2026 | D336: 2033649140 00 | E336: Deamonte Maree | F336: Cancel | G336: 6/29/2026 | H336: -802 | I336: -802 | J336: 0.1 | K336: -80.2 | L336: =ROUND(I336*J336,2) -> -80.2 | M336: =K336-L336 -> 0 | N336: =IF(F336="Promotional Incentive",0,I336) -> -802 | O336: =IF(F336="Promotional Incentive",0,K336) -> -80.2 | P336: No
... A338: National General|203613405400 | B338: National General | C338: National General Commission Stmt 06/2026 | D338: 2036134054 00 | E338: Carlos Sanchez | F338: New Business | G338: 6/19/2026 | H338: 3257 | I338: 3257 | J338: 0.1 | K338: 325.7 | L338: =ROUND(I338*J338,2) -> 325.7 | M338: =K338-L338 -> 0 | N338: =IF(F338="Promotional Incentive",0,I338) -> 3257 | O338: =IF(F338="Promotional Incentive",0,K338) -> 325.7 | P338: No
A339: AmWins|FFL1008512 | B339: AmWins | C339: Amwins Specialty Auto Commission Stmt 06/2026 | D339: FFL01008512 | E339: GEJO ANGELY | F339: Commission | G339: 06/29/2026 | H339: 248 | I339: 164.67 | J339: 0.1 | K339: 16.47 | L339: =ROUND(I339*J339,2) -> 16.47 | M339: =K339-L339 -> 0 | N339: =IF(F339="Promotional Incentive",0,I339) -> 164.67 | O339: =IF(F339="Promotional Incentive",0,K339) -> 16.47 | P339: YES | Q339: ANGELY GEJO
A340: AmWins|FFL1033783 | B340: AmWins | C340: Amwins Specialty Auto Commission Stmt 06/2026 | D340: FFL01033783 | E340: QUINONES SANCHEZ LUIS | F340: Commission | G340: 06/30/2026 | H340: 0 | I340: 77.5 | J340: 0.1 | K340: 7.75 | L340: =ROUND(I340*J340,2) -> 7.75 | M340: =K340-L340 -> 0 | N340: =IF(F340="Promotional Incentive",0,I340) -> 77.5 | O340: =IF(F340="Promotional Incentive",0,K340) -> 7.75 | P340: YES | Q340: LUIS QUINONES SANCHEZ
A341: AmWins|FFL1067788 | B341: AmWins | C341: Amwins Specialty Auto Commission Stmt 06/2026 | D341: FFL01067788 | E341: PETIT-HOMME JEFFREY BO | F341: Commission | G341: 06/17/2026 | H341: 0 | I341: 178.5 | J341: 0.1 | K341: 17.85 | L341: =ROUND(I341*J341,2) -> 17.85 | M341: =K341-L341 -> 0 | N341: =IF(F341="Promotional Incentive",0,I341) -> 178.5 | O341: =IF(F341="Promotional Incentive",0,K341) -> 17.85 | P341: YES | Q341: JEFFREY B. PETIT-HOMME
A342: AmWins|FFL1014574 | B342: AmWins | C342: Amwins Specialty Auto Commission Stmt 06/2026 | D342: FFL01014574 | E342: O BRIEN CHLOE L | F342: Commission | G342: 03/01/2026 | H342: 0 | I342: 105.83 | J342: 0.1 | K342: 10.58 | L342: =ROUND(I342*J342,2) -> 10.58 | M342: =K342-L342 -> 0 | N342: =IF(F342="Promotional Incentive",0,I342) -> 105.83 | O342: =IF(F342="Promotional Incentive",0,K342) -> 10.58 | P342: No
A343: AmWins|FFL1036461 | B343: AmWins | C343: Amwins Specialty Auto Commission Stmt 06/2026 | D343: FFL01036461 | E343: GRAHAM ANAIYA | F343: Commission | G343: 01/24/2026 | H343: -87 | I343: 0.65 | J343: 0.1 | K343: 0.07 | L343: =ROUND(I343*J343,2) -> 0.07 | M343: =K343-L343 -> 0 | N343: =IF(F343="Promotional Incentive",0,I343) -> 0.65 | O343: =IF(F343="Promotional Incentive",0,K343) -> 0.07 | P343: No
A344: AmWins|FFL1060899 | B344: AmWins | C344: Amwins Specialty Auto Commission Stmt 06/2026 | D344: FFL01060899 | E344: JACUZZI NINA S | F344: Commission | G344: 01/23/2026 | H344: 0 | I344: 100 | J344: 0.1 | K344: 10 | L344: =ROUND(I344*J344,2) -> 10 | M344: =K344-L344 -> 0 | N344: =IF(F344="Promotional Incentive",0,I344) -> 100 | O344: =IF(F344="Promotional Incentive",0,K344) -> 10 | P344: No
...

Sheet Carrier Recap
A1: Recap by Carrier - Doral Binder Book vs. Full Carrier Statement
A3: Carrier | B3: Commission Statement | C3: Rate the Carrier Shows | D3: Binder Policies | E3: Found on Statement | F3: Commissionable Premium (binder clients) | G3: Commission Earned (binder clients) | H3: Total Commission on Statement (all agency business) | I3: Binder Share of Statement | J3: Other Book Activity - Txns | K3: Other Book Activity - Commission | L3: Statement Adjustments (Doral) | M3: Total Doral Commission
A4: Progressive | B4: Progressive Detailed Statement 06/2026 | C4: 8% - 14%, varies by policy | D4: 36 | E4: =SUMPRODUCT(('Commission Summary'!$F$6:$F$74=$A4)*('Commission Summary'!$L$6:$L$74>0)) -> 30 | F4: =SUMIF('Commission Summary'!$F$6:$F$74,$A4,'Commission Summary'!$N$6:$N$74) -> 42357.06 | G4: =SUMIF('Commission Summary'!$F$6:$F$74,$A4,'Commission Summary'!$O$6:$O$74) -> 4351.14 | H4: =SUMIF('Transaction Detail'!$B$2:$B$385,$A4,'Transaction Detail'!$K$2:$K$385) -> 14289.02 | I4: =IF(H4=0,"",G4/H4) -> 0.30450934 | J4: 25 | K4: ='Book Activity by Carrier'!J31 -> 64.35 | L4: =SUMIFS('Book Activity by Carrier'!$F$135:$F$162,'Book Activity by Carrier'!$C$135:$C$162,"Progressive",'Book Activity by Carrier'!$J$135:$J$162,"YES") -> 0 | M4: =G4+K4+L4 -> 4415.49
A5: Infinity | B5: Kemper Auto Monthly Producer Stmt 06/2026 | C5: 10% flat | D5: 9 | E5: =SUMPRODUCT(('Commission Summary'!$F$6:$F$74=$A5)*('Commission Summary'!$L$6:$L$74>0)) -> 5 | F5: =SUMIF('Commission Summary'!$F$6:$F$74,$A5,'Commission Summary'!$N$6:$N$74) -> 5802 | G5: =SUMIF('Commission Summary'!$F$6:$F$74,$A5,'Commission Summary'!$O$6:$O$74) -> 580.2 | H5: =SUMIF('Transaction Detail'!$B$2:$B$385,$A5,'Transaction Detail'!$K$2:$K$385) -> 656.6 | I5: =IF(H5=0,"",G5/H5) -> 0.88364301 | J5: 8 | K5: ='Book Activity by Carrier'!J42 -> -692.6 | L5: =SUMIFS('Book Activity by Carrier'!$F$135:$F$162,'Book Activity by Carrier'!$C$135:$C$162,"Infinity",'Book Activity by Carrier'!$J$135:$J$162,"YES") -> 0 | M5: =G5+K5+L5 -> -112.4
A6: United Auto | B6: United Insurance Group Direct Billing Stmt 06/2026 | C6: 10% as collected (3% incentive excluded) | D6: 10 | E6: =SUMPRODUCT(('Commission Summary'!$F$6:$F$74=$A6)*('Commission Summary'!$L$6:$L$74>0)) -> 10 | F6: =SUMIF('Commission Summary'!$F$6:$F$74,$A6,'Commission Summary'!$N$6:$N$74) -> 9025.3 | G6: =SUMIF('Commission Summary'!$F$6:$F$74,$A6,'Commission Summary'!$O$6:$O$74) -> 902.53 | H6: =SUMIF('Transaction Detail'!$B$2:$B$385,$A6,'Transaction Detail'!$K$2:$K$385) -> 444.33 | I6: =IF(H6=0,"",G6/H6) -> 2.0312155 | J6: 58 | K6: ='Book Activity by Carrier'!J103 -> -657.67 | L6: =SUMIFS('Book Activity by Carrier'!$F$135:$F$162,'Book Activity by Carrier'!$C$135:$C$162,"United Auto",'Book Activity by Carrier'!$J$135:$J$162,"YES") -> 0 | M6: =G6+K6+L6 -> 244.86
A7: Ocean Harbor | B7: Pearl Holding Group Commission Stmt 06/2026 | C7: 11% (13% on some policies) | D7: 2 | E7: =SUMPRODUCT(('Commission Summary'!$F$6:$F$74=$A7)*('Commission Summary'!$L$6:$L$74>0)) -> 2 | F7: =SUMIF('Commission Summary'!$F$6:$F$74,$A7,'Commission Summary'!$N$6:$N$74) -> 2294 | G7: =SUMIF('Commission Summary'!$F$6:$F$74,$A7,'Commission Summary'!$O$6:$O$74) -> 252.34 | H7: =SUMIF('Transaction Detail'!$B$2:$B$385,$A7,'Transaction Detail'!$K$2:$K$385) -> 326.21 | I7: =IF(H7=0,"",G7/H7) -> 0.77355078 | J7: 2 | K7: ='Book Activity by Carrier'!J108 -> -60.11 | L7: =SUMIFS('Book Activity by Carrier'!$F$135:$F$162,'Book Activity by Carrier'!$C$135:$C$162,"Ocean Harbor",'Book Activity by Carrier'!$J$135:$J$162,"YES") -> -8.36 | M7: =G7+K7+L7 -> 183.87
A8: National General | B8: National General Commission Stmt 06/2026 | C8: 10% flat | D8: 3 | E8: =SUMPRODUCT(('Commission Summary'!$F$6:$F$74=$A8)*('Commission Summary'!$L$6:$L$74>0)) -> 2 | F8: =SUMIF('Commission Summary'!$F$6:$F$74,$A8,'Commission Summary'!$N$6:$N$74) -> 2334 | G8: =SUMIF('Commission Summary'!$F$6:$F$74,$A8,'Commission Summary'!$O$6:$O$74) -> 233.4 | H8: =SUMIF('Transaction Detail'!$B$2:$B$385,$A8,'Transaction Detail'!$K$2:$K$385) -> 871.27 | I8: =IF(H8=0,"",G8/H8) -> 0.26788481 | J8: 7 | K8: ='Book Activity by Carrier'!J118 -> -202.23 | L8: =SUMIFS('Book Activity by Carrier'!$F$135:$F$162,'Book Activity by Carrier'!$C$135:$C$162,"National General",'Book Activity by Carrier'!$J$135:$J$162,"YES") -> -35.06 | M8: =G8+K8+L8 -> -3.89
A9: AmWins | B9: Amwins Specialty Auto Commission Stmt 06/2026 | C9: 10% of net cash | D9: 3 | E9: =SUMPRODUCT(('Commission Summary'!$F$6:$F$74=$A9)*('Commission Summary'!$L$6:$L$74>0)) -> 3 | F9: =SUMIF('Commission Summary'!$F$6:$F$74,$A9,'Commission Summary'!$N$6:$N$74) -> 420.67 | G9: =SUMIF('Commission Summary'!$F$6:$F$74,$A9,'Commission Summary'!$O$6:$O$74) -> 42.07 | H9: =SUMIF('Transaction Detail'!$B$2:$B$385,$A9,'Transaction Detail'!$K$2:$K$385) -> 72.34 | I9: =IF(H9=0,"",G9/H9) -> 0.5815593 | J9: 1 | K9: ='Book Activity by Carrier'!J122 -> 0.07 | L9: =SUMIFS('Book Activity by Carrier'!$F$135:$F$162,'Book Activity by Carrier'!$C$135:$C$162,"AmWins",'Book Activity by Carrier'!$J$135:$J$162,"YES") -> 0 | M9: =G9+K9+L9 -> 42.14
A10: GEICO | B10: GEICO Commission Statement 06/2026 | C10: 10% / 12% / 15% | D10: 0 | E10: 0 | F10: 0 | G10: 0 | H10: =SUMIF('Transaction Detail'!$B$2:$B$385,$A10,'Transaction Detail'!$K$2:$K$385) -> 2267.79 | J10: 2 | K10: ='Book Activity by Carrier'!J127 -> -45.78 | L10: =SUMIFS('Book Activity by Carrier'!$F$135:$F$162,'Book Activity by Carrier'!$C$135:$C$162,"GEICO",'Book Activity by Carrier'!$J$135:$J$162,"YES") -> 0 | M10: =G10+K10+L10 -> -45.78
A11: TOTAL | D11: =SUM(D4:D10) -> 63 | E11: =SUM(E4:E10) -> 52 | F11: =SUM(F4:F10) -> 62233.03 | G11: =SUM(G4:G10) -> 6361.68 | H11: =SUM(H4:H10) -> 18927.56 | I11: =IF(H11=0,"",G11/H11) -> 0.33610671 | J11: =SUM(J4:J10) -> 103 | K11: =SUM(K4:K10) -> -1593.97 | L11: =SUM(L4:L10) -> -43.42 | M11: =SUM(M4:M10) -> 4724.29

Sheet Book Activity by Carrier
A1: Other Doral Book Activity on the June 2026 Carrier Statements
A2: Transactions belonging to the wider Doral office book of business that appear on the June carrier statements but are NOT on the June binder sheet - endorsements, cancellations, adjustments and as-collected commission on policies written in earlier months.
A4: Customer Name (per Doral book) | B4: Policy Number | C4: Insured Name (per statement) | D4: Transaction Type | E4: Transaction Date | F4: Premium / Basis | G4: Premium Counted | H4: Carrier Comm Rate | I4: Commission per Statement | J4: Commission Counted | K4: Book Month | L4: Company (per book)
A5: PROGRESSIVE - 25 transactions
A6: IVAN D MOLINA LOZANO | B6: 862085078 | C6: MOLINA LOZAN I. | D6: Endorsement | E6: 06/06/2026 | F6: 299.97 | G6: =IF(D6="Promotional Incentive",0,F6) -> 299.97 | H6: 0.1 | I6: 30 | J6: =IF(D6="Promotional Incentive",0,I6) -> 30 | K6: FEB 26 | L6: Progressive
A7: GUILLERMO FAYAS RODRIGUEZ | B7: 867943703 | C7: FAYAS RODRIG G. | D7: Renewal | E7: 07/08/2026 | F7: 1794 | G7: =IF(D7="Promotional Incentive",0,F7) -> 1794 | H7: 0.1 | I7: 179.4 | J7: =IF(D7="Promotional Incentive",0,I7) -> 179.4 | K7: JULY 26 | L7: Progressive
A8: KATHERINE A FERNANDEZ | B8: 869341373 | C8: FERNANDEZ K. | D8: Cancel Pro Rate | E8: 06/05/2026 | F8: -592.29 | G8: =IF(D8="Promotional Incentive",0,F8) -> -592.29 | H8: 0.1 | I8: -59.23 | J8: =IF(D8="Promotional Incentive",0,I8) -> -59.23 | K8: FEB 26 | L8: Progressive
A9: IVAN S FLORES JARAMILLO | B9: 869745230 | C9: FLORES JARAM I. | D9: Endorsement | E9: 06/10/2026 | F9: 0 | G9: =IF(D9="Promotional Incentive",0,F9) -> 0 | H9: 0.1 | I9: 0 | J9: =IF(D9="Promotional Incentive",0,I9) -> 0 | K9: FEB 26 | L9: Progressive
A10: CAROL J SAFI | B10: 871135598 | C10: SAFI C. | D10: Credit Endorsement | E10: 06/09/2026 | F10: -133.12 | G10: =IF(D10="Promotional Incentive",0,F10) -> -133.12 | H10: 0.1 | I10: -13.31 | J10: =IF(D10="Promotional Incentive",0,I10) -> -13.31 | K10: data march | L10: Progressive
A11: JUAN J ORTUNO | B11: 871466655 | C11: ORTUNO J. | D11: Credit Endorsement | E11: 06/12/2026 | F11: -26.08 | G11: =IF(D11="Promotional Incentive",0,F11) -> -26.08 | H11: 0.1 | I11: -2.61 | J11: =IF(D11="Promotional Incentive",0,I11) -> -2.61 | K11: data march | L11: Progressive
A12: DAVID GUERRA | B12: 872036378 | C12: GUERRA D. | D12: Cancel Pro Rate | E12: 06/29/2026 | F12: -736.55 | G12: =IF(D12="Promotional Incentive",0,F12) -> -736.55 | H12: 0.12 | I12: -88.39 | J12: =IF(D12="Promotional Incentive",0,I12) -> -88.39 | K12: data april | L12: Progressive
A13: PAULINA GUERRERO | B13: 872333790 | C13: GUERRERO P. | D13: Cancel Pro Rate | E13: 06/29/2026 | F13: -579.3 | G13: =IF(D13="Promotional Incentive",0,F13) -> -579.3 | H13: 0.1 | I13: -57.93 | J13: =IF(D13="Promotional Incentive",0,I13) -> -57.93 | K13: data april | L13: Progressive
A14: JOSE MICO I. | B14: 872526456 | C14: MICO IZQUIER J. | D14: Endorsement | E14: 06/09/2026 | F14: 100.14 | G14: =IF(D14="Promotional Incentive",0,F14) -> 100.14 | H14: 0.1 | I14: 10.01 | J14: =IF(D14="Promotional Incentive",0,I14) -> 10.01 | K14: data april | L14: Progressive
A15: JOSE MICO I. | B15: 872526456 | C15: MICO IZQUIER J. | D15: Cancel Pro Rate | E15: 07/01/2026 | F15: -1413.68 | G15: =IF(D15="Promotional Incentive",0,F15) -> -1413.68 | H15: 0.1 | I15: -141.37 | J15: =IF(D15="Promotional Incentive",0,I15) -> -141.37 | K15: data april | L15: Progressive
A16: ROSS M LAZAREK | B16: 873197162 | C16: LAZAREK R. | D16: Credit Endorsement | E16: 06/15/2026 | F16: -33.64 | G16: =IF(D16="Promotional Incentive",0,F16) -> -33.64 | H16: 0.14 | I16: -4.71 | J16: =IF(D16="Promotional Incentive",0,I16) -> -4.71 | K16: data april | L16: Progressive
A17: JOSE DIAZ | B17: 874616317 | C17: DIAZ J. | D17: Cancel Pro Rate | E17: 05/27/2026 | F17: -744.72 | G17: =IF(D17="Promotional Incentive",0,F17) -> -744.72 | H17: 0.1 | I17: -74.47 | J17: =IF(D17="Promotional Incentive",0,I17) -> -74.47 | K17: data may | L17: Progressive
... A30: EMILEY BLOMBERG | B30: 999745921 | C30: BLOMBERG E. | D30: Renewal | E30: 07/03/2026 | F30: 2048 | G30: =IF(D30="Promotional Incentive",0,F30) -> 2048 | H30: 0.1 | I30: 204.8 | J30: =IF(D30="Promotional Incentive",0,I30) -> 204.8 | K30: JULY 26 | L30: Progressive
A31: Progressive subtotal | F31: =SUM(F6:F30) -> 558.91 | G31: =SUM(G6:G30) -> 558.91 | I31: =SUM(I6:I30) -> 64.35 | J31: =SUM(J6:J30) -> 64.35
A33: INFINITY - 8 transactions
A34: RESUL TAS | B34: 10193915602 | C34: TAS, RESUL | D34: New | E34: 06/17/2026 | F34: 361 | G34: =IF(D34="Promotional Incentive",0,F34) -> 361 | H34: 0.1 | I34: 36.1 | J34: =IF(D34="Promotional Incentive",0,I34) -> 36.1 | K34: FEB 25 | L34: Infinity
A35: JUAN PEREZ ROY | B35: 10213255201 | C35: PEREZ ROY, JUAN | D35: CnxFinal | E35: 05/23/2026 | F35: -584 | G35: =IF(D35="Promotional Incentive",0,F35) -> -584 | H35: 0.1 | I35: -58.4 | J35: =IF(D35="Promotional Incentive",0,I35) -> -58.4 | K35: JULIO 25 | L35: Infinity
A36: JUAN PEREZ ROY | B36: 10213255201 | C36: PEREZ ROY, JUAN | D36: CnxFinal | E36: 06/29/2026 | F36: -2950 | G36: =IF(D36="Promotional Incentive",0,F36) -> -2950 | H36: 0.1 | I36: -295 | J36: =IF(D36="Promotional Incentive",0,I36) -> -295 | K36: JULIO 25 | L36: Infinity
A37: SYLVESTER FRATER | B37: 10239866201 | C37: FRATER, SYLVESTER | D37: CnxFinal | E37: 06/14/2026 | F37: -460 | G37: =IF(D37="Promotional Incentive",0,F37) -> -460 | H37: 0.1 | I37: -46 | J37: =IF(D37="Promotional Incentive",0,I37) -> -46 | K37: JULIO 25 | L37: Infinity
A38: DIVYANI RAI | B38: 10260538001 | C38: RAI, DIVYANI | D38: ENDORSE | E38: 06/20/2026 | F38: -6 | G38: =IF(D38="Promotional Incentive",0,F38) -> -6 | H38: 0.1 | I38: -0.6 | J38: =IF(D38="Promotional Incentive",0,I38) -> -0.6 | K38: data march | L38: Infinity
A39: DIVYANI RAI | B39: 10260538001 | C39: RAI, DIVYANI | D39: ENDORSE | E39: 06/20/2026 | F39: -44 | G39: =IF(D39="Promotional Incentive",0,F39) -> -44 | H39: 0.1 | I39: -4.4 | J39: =IF(D39="Promotional Incentive",0,I39) -> -4.4 | K39: data march | L39: Infinity
A40: JABIERQUIS MENDOZA | B40: 10260713001 | C40: MENDOZA, JABIERQUIS | D40: CnxFinal | E40: 06/03/2026 | F40: -698 | G40: =IF(D40="Promotional Incentive",0,F40) -> -698 | H40: 0.1 | I40: -69.8 | J40: =IF(D40="Promotional Incentive",0,I40) -> -69.8 | K40: data march | L40: Infinity
A41: JORGE O RIVAS (STREN DISTRIBUTOR) | B41: 50026396402 | C41: RIVAS, JORGE | D41: CnxFinal | E41: 06/24/2026 | F41: -2545 | G41: =IF(D41="Promotional Incentive",0,F41) -> -2545 | H41: 0.1 | I41: -254.5 | J41: =IF(D41="Promotional Incentive",0,I41) -> -254.5 | K41: FEB 26 | L41: Infinity
A42: Infinity subtotal | F42: =SUM(F34:F41) -> -6926 | G42: =SUM(G34:G41) -> -6926 | I42: =SUM(I34:I41) -> -692.6 | J42: =SUM(J34:J41) -> -692.6
A44: UNITED AUTO - 58 transactions
A45: VICTOR GARCIA BARRERAS | B45: UAD 602082206 | C45: VICTOR E GARCIA BARRE | D45: Comm as Collected | E45: 06/30/26 | F45: 269.1 | G45: =IF(D45="Promotional Incentive",0,F45) -> 269.1 | H45: 0.1 | I45: 26.91 | J45: =IF(D45="Promotional Incentive",0,I45) -> 26.91 | K45: FEB 26 | L45: United Auto
A46: TIMMIE ROZIER | B46: UAD 606159902 | C46: TIMMIE ROZIER | D46: Comm as Collected | E46: 06/30/26 | F46: 178.9 | G46: =IF(D46="Promotional Incentive",0,F46) -> 178.9 | H46: 0.1 | I46: 17.89 | J46: =IF(D46="Promotional Incentive",0,I46) -> 17.89 | K46: JULY 26 | L46: United Auto
A47: BIANCA R. BUZZIZ | B47: UAD 606715305 | C47: BIANCA R BUZZIZ | D47: Comm as Collected | E47: 06/30/26 | F47: 212.9 | G47: =IF(D47="Promotional Incentive",0,F47) -> 212.9 | H47: 0.1 | I47: 21.29 | J47: =IF(D47="Promotional Incentive",0,I47) -> 21.29 | K47: FEB 26 | L47: United Auto
A48: ORESTE CANIZARES GONZALEZ | B48: UAD 607888404 | C48: ORESTE CANIZARES GONZ | D48: Comm as Collected | E48: 06/30/26 | F48: 202.2 | G48: =IF(D48="Promotional Incentive",0,F48) -> 202.2 | H48: 0.1 | I48: 20.22 | J48: =IF(D48="Promotional Incentive",0,I48) -> 20.22 | K48: data may | L48: United Auto
A49: ORESTE CANIZARES GONZALEZ | B49: UAD 607888404 | C49: ORESTE CANIZARES GONZ | D49: Promotional Incentive | E49: 06/30/26 | F49: 202.2 | G49: =IF(D49="Promotional Incentive",0,F49) -> 0 | H49: 0.03 | I49: 6.06 | J49: =IF(D49="Promotional Incentive",0,I49) -> 0 | K49: data may | L49: United Auto
A50: JOSE ANTONIO CRUZ PEREZ | B50: UAE 000217449 | C50: JOSE A CRUZ PEREZ | D50: Comm as Collected | E50: 06/30/26 | F50: 420.7 | G50: =IF(D50="Promotional Incentive",0,F50) -> 420.7 | H50: 0.1 | I50: 42.07 | J50: =IF(D50="Promotional Incentive",0,I50) -> 42.07 | K50: JULIO 25 | L50: United Auto
A51: JUAN J PAYANO | B51: UAE 000225427 | C51: JUAN J PAYANO | D51: Comm as Collected | E51: 06/30/26 | F51: 190.6 | G51: =IF(D51="Promotional Incentive",0,F51) -> 190.6 | H51: 0.1 | I51: 19.06 | J51: =IF(D51="Promotional Incentive",0,I51) -> 19.06 | K51: JULIO 25 | L51: United Auto
A52: LUIS MARIO ORTUNO | B52: UAE 000254009 | C52: LUIS M ORTUNO | D52: Comm as Collected | E52: 06/30/26 | F52: 94.4 | G52: =IF(D52="Promotional Incentive",0,F52) -> 94.4 | H52: 0.1 | I52: 9.44 | J52: =IF(D52="Promotional Incentive",0,I52) -> 9.44 | K52: NOV 25 | L52: United Auto
A53: KENOLD MERVEILLE | B53: UAE 000268427 | C53: KENOLD MERVEILLE | D53: Endorsement | E53: 06/28/26 | F53: 0 | G53: =IF(D53="Promotional Incentive",0,F53) -> 0 | H53: 0.1 | I53: 0 | J53: =IF(D53="Promotional Incentive",0,I53) -> 0 | K53: data march | L53: United Auto
A54: KENOLD MERVEILLE | B54: UAE 000268427 | C54: KENOLD MERVEILLE | D54: Promotional Incentive | E54: 06/28/26 | F54: 0 | G54: =IF(D54="Promotional Incentive",0,F54) -> 0 | H54: 0.03 | I54: 0 | J54: =IF(D54="Promotional Incentive",0,I54) -> 0 | K54: data march | L54: United Auto
A55: MIRLOUDE PETIT FRERE | B55: UAH 000518008 | C55: MIRLOUDE PETIT FRERE | D55: Cancel (Prorate) | E55: 06/16/26 | F55: -2598 | G55: =IF(D55="Promotional Incentive",0,F55) -> -2598 | H55: 0.1 | I55: -259.8 | J55: =IF(D55="Promotional Incentive",0,I55) -> -259.8 | K55: data april | L55: United Auto
A56: MIRLOUDE PETIT FRERE | B56: UAH 000518008 | C56: MIRLOUDE PETIT FRERE | D56: Promotional Incentive | E56: 06/16/26 | F56: -2598 | G56: =IF(D56="Promotional Incentive",0,F56) -> 0 | H56: 0.03 | I56: -77.94 | J56: =IF(D56="Promotional Incentive",0,I56) -> 0 | K56: data april | L56: United Auto
... A102: LIZ B. LOPEZ (done by Alberto) | B102: UAO 062029201 | C102: LIZ B LOPEZ | D102: Comm as Collected | E102: 06/30/26 | F102: 177.3 | G102: =IF(D102="Promotional Incentive",0,F102) -> 177.3 | H102: 0.1 | I102: 17.73 | J102: =IF(D102="Promotional Incentive",0,I102) -> 17.73 | K102: FEB 26 | L102: United Auto
A103: United Auto subtotal | F103: =SUM(F45:F102) -> -15453.4 | G103: =SUM(G45:G102) -> -6576.7 | I103: =SUM(I45:I102) -> -923.99 | J103: =SUM(J45:J102) -> -657.67
A105: OCEAN HARBOR - 2 transactions
A106: JAHMAR J JOHNSON | B106: P020109544801 | C106: JOHNSON, JAHMAR J | D106: Cancellation | E106: 06/01/2026 | F106: -434 | G106: =IF(D106="Promotional Incentive",0,F106) -> -434 | H106: 0.13 | I106: -56.42 | J106: =IF(D106="Promotional Incentive",0,I106) -> -56.42 | K106: ENER 26 | L106: Ocean Harbor
A107: JAHMAR J JOHNSON | B107: P020109544801 | C107: JOHNSON, JAHMAR J | D107: Uncollected Premium | E107: 06/01/2026 | F107: -28.42 | G107: =IF(D107="Promotional Incentive",0,F107) -> -28.42 | H107: 0.13 | I107: -3.69 | J107: =IF(D107="Promotional Incentive",0,I107) -> -3.69 | K107: ENER 26 | L107: Ocean Harbor
A108: Ocean Harbor subtotal | F108: =SUM(F106:F107) -> -462.42 | G108: =SUM(G106:G107) -> -462.42 | I108: =SUM(I106:I107) -> -60.11 | J108: =SUM(J106:J107) -> -60.11
A110: NATIONAL GENERAL - 7 transactions
A111: EVICSON CRESPO | B111: 2021843298 04 | C111: Evicson Crespo | D111: Endorsement | E111: 6/6/2026 | F111: -42 | G111: =IF(D111="Promotional Incentive",0,F111) -> -42 | H111: 0.1 | I111: -4.2 | J111: =IF(D111="Promotional Incentive",0,I111) -> -4.2 | K111: FEB 26 | L111: National General
A112: MAKIYAH MOORE | B112: 2022375481 04 | C112: Makiyah Moore | D112: Endorsement | E112: 6/23/2026 | F112: 69 | G112: =IF(D112="Promotional Incentive",0,F112) -> 69 | H112: 0.1 | I112: 6.9 | J112: =IF(D112="Promotional Incentive",0,I112) -> 6.9 | K112: data march | L112: National General
A113: ERGLYN ZAMBRANO | B113: 2024704234 02 | C113: Erglyn Zambrano | D113: Uncollected Premium | E113: 2/17/2026 | F113: -57.3 | G113: =IF(D113="Promotional Incentive",0,F113) -> -57.3 | H113: 0.1 | I113: -5.73 | J113: =IF(D113="Promotional Incentive",0,I113) -> -5.73 | K113: SET 25 | L113: National General
A114: DAYANA CANOVA | B114: 2031162171 01 | C114: Dayana Canova | D114: Endorsement | E114: 6/15/2026 | F114: 4 | G114: =IF(D114="Promotional Incentive",0,F114) -> 4 | H114: 0.1 | I114: 0.4 | J114: =IF(D114="Promotional Incentive",0,I114) -> 0.4 | K114: data march | L114: National General
A115: SINDY MOLINA | B115: 2032132924 01 | C115: Sindy Molina | D115: Cancel | E115: 6/23/2026 | F115: -791 | G115: =IF(D115="Promotional Incentive",0,F115) -> -791 | H115: 0.1 | I115: -79.1 | J115: =IF(D115="Promotional Incentive",0,I115) -> -79.1 | K115: data may | L115: National General
A116: KEVIN D. JIMENEZ AGUERO | B116: 2033211242 00 | C116: Kevin Jimenez Aguero | D116: Endorsement | E116: 6/2/2026 | F116: 312 | G116: =IF(D116="Promotional Incentive",0,F116) -> 312 | H116: 0.1 | I116: 31.2 | J116: =IF(D116="Promotional Incentive",0,I116) -> 31.2 | K116: JULY 26 | L116: National General
A117: CHRISTIAN RIVERO | B117: 2035032222 00 | C117: Christian Rivero | D117: Cancel | E117: 6/2/2026 | F117: -1517 | G117: =IF(D117="Promotional Incentive",0,F117) -> -1517 | H117: 0.1 | I117: -151.7 | J117: =IF(D117="Promotional Incentive",0,I117) -> -151.7 | K117: data april | L117: National General
A118: National General subtotal | F118: =SUM(F111:F117) -> -2022.3 | G118: =SUM(G111:G117) -> -2022.3 | I118: =SUM(I111:I117) -> -202.23 | J118: =SUM(J111:J117) -> -202.23
A120: AMWINS - 1 transaction
A121: ANAIYA GRAHAM | B121: FFL01036461 | C121: GRAHAM ANAIYA | D121: Commission | E121: 01/24/2026 | F121: 0.65 | G121: =IF(D121="Promotional Incentive",0,F121) -> 0.65 | H121: 0.1 | I121: 0.07 | J121: =IF(D121="Promotional Incentive",0,I121) -> 0.07 | K121: JULY 24 | L121: AmWins
A122: AmWins subtotal | F122: =SUM(F121:F121) -> 0.65 | G122: =SUM(G121:G121) -> 0.65 | I122: =SUM(I121:I121) -> 0.07 | J122: =SUM(J121:J121) -> 0.07
A124: GEICO - 2 transactions
A125: IRIS LOPEZ SANCHEZ | B125: 6219586788-442580316 | C125: IRIS LOPEZ SANCHEZ | D125: Renewal Year Commission | E125: 06/09/2026 | F125: -402.75 | G125: =IF(D125="Promotional Incentive",0,F125) -> -402.75 | H125: 0.12 | I125: -48.33 | J125: =IF(D125="Promotional Incentive",0,I125) -> -48.33 | K125: geico | L125: Geico
A126: IRIS LOPEZ SANCHEZ | B126: 6219586788-442580316 | C126: IRIS LOPEZ SANCHEZ | D126: Renewal Year Commission | E126: 06/09/2026 | F126: 21.21 | G126: =IF(D126="Promotional Incentive",0,F126) -> 21.21 | H126: 0.12 | I126: 2.55 | J126: =IF(D126="Promotional Incentive",0,I126) -> 2.55 | K126: geico | L126: Geico
A127: GEICO subtotal | F127: =SUM(F125:F126) -> -381.54 | G127: =SUM(G125:G126) -> -381.54 | I127: =SUM(I125:I126) -> -45.78 | J127: =SUM(J125:J126) -> -45.78
A129: TOTAL - OTHER DORAL BOOK ACTIVITY | F129: =F31+F42+F103+F108+F118+F122+F127 -> -24686.1 | G129: =G31+G42+G103+G108+G118+G122+G127 -> -15809.4 | I129: =I31+I42+I103+I108+I118+I122+I127 -> -1860.29 | J129: =J31+J42+J103+J108+J118+J122+J127 -> -1593.97
A132: STATEMENT-LEVEL ADJUSTMENTS & FEES
A133: Every chargeback, fee and adjustment the carriers apply outside the policy transaction listing. Four carriers have them: National General, Kemper, Pearl and United. Most carry no policy number, so they are matched by name where the carrier gives one. Only rows marked YES reach the totals - a row can be Doral business and still be excluded, as United's 3% is.
A134: Name on the adjustment | B134: Reference | C134: Carrier | D134: Adjustment Type | E134: Date | F134: Amount | J134: Counted? | K134: Book Month | L134: How it was matched / why not counted
A135: UW Reports fee FL - 23 | B135: Agent 5517897 | C135: Infinity | D135: Fee - UW Reports | E135: 06/30/2026 | F135: -10.35 | J135: No | L135: Agency-level fee - Kemper names no insured, so it cannot be attributed to the Doral book
A136: UW Reports fee FL - 90 | B136: Agent 5517897 | C136: Infinity | D136: Fee - UW Reports | E136: 06/30/2026 | F136: -22.55 | J136: No | L136: Agency-level fee - Kemper names no insured, so it cannot be attributed to the Doral book
A137: 3% promotional incentive on June binder-sheet policies | B137: Agent 001-1D-100208 | C137: United Auto | D137: Promotional Incentive | E137: 06/30/26 | F137: 252.85 | J137: No | K137: 9 lines | L137: United books its 3% incentive as an Adjustment (its statement shows 37 such lines netting $6.89 agency-wide). Excluded by instruction - this book is carried at 10% as collected. Every line is itemised on the Transaction Detail and Book Activity tabs.
A138: 3% promotional incentive on wider Doral book policies | B138: Agent 001-1D-100208 | C138: United Auto | D138: Promotional Incentive | E138: 06/30/26 | F138: -266.32 | J138: No | K138: 23 lines | L138: United books its 3% incentive as an Adjustment (its statement shows 37 such lines netting $6.89 agency-wide). Excluded by instruction - this book is carried at 10% as collected. Every line is itemised on the Transaction Detail and Book Activity tabs.
A139: JAHMAR JOHNSON | B139: Producer 6883 | C139: Ocean Harbor | D139: MVR Cost | E139: 06/22/2026 | F139: -8.36 | J139: YES | K139: JULY 26 | L139: Name abbreviated by Pearl; matched to Jahmar J Johnson, who is on this same statement
A140: MARTINEZ, L | B140: Producer 6883 | C140: Ocean Harbor | D140: MVR Cost | E140: 06/05/2026 | F140: -8.36 | J140: No | L140: Name abbreviated by Pearl - no confident Doral match
A141: JOSE ABREU | B141: Quote 242804983 | C141: National General | D141: Viol Hist Chargeback | E141: 4/9/2026 | F141: -9.02 | J141: YES | K141: JULY 26 | L141: Matched by name and quote number - this section carries no policy number
A142: CHARLIE HOZ | B142: Quote 245836859 | C142: National General | D142: Loss Hist Chargeback | E142: 4/28/2026 | F142: -1 | J142: YES | K142: data april | L142: Matched by name and quote number - this section carries no policy number
A143: FERNANDO RODRIGUEZ | B143: Quote 242948950 | C143: National General | D143: Loss Hist Chargeback | E143: 4/10/2026 | F143: -1 | J143: YES | K143: FEB 24 | L143: Matched by name and quote number - this section carries no policy number
A144: GAVONEEY Q. WILSON | B144: Quote 242639442 | C144: National General | D144: Loss Hist Chargeback | E144: 4/8/2026 | F144: -1 | J144: YES | K144: data april | L144: Matched by name and quote number - this section carries no policy number
A145: JOSE ABREU | B145: Quote 242804983 | C145: National General | D145: Loss Hist Chargeback | E145: 4/9/2026 | F145: -1 | J145: YES | K145: JULY 26 | L145: Matched by name and quote number - this section carries no policy number
A146: JULIO OVIOL | B146: Quote 244079950 | C146: National General | D146: Loss Hist Chargeback | E146: 4/17/2026 | F146: -1 | J146: YES | K146: data april | L146: Matched by name and quote number - this section carries no policy number
A147: KIMBERLY MUNIZ | B147: Quote 242985155 | C147: National General | D147: Loss Hist Chargeback | E147: 4/10/2026 | F147: -1 | J147: YES | K147: data april | L147: Matched by name and quote number - this section carries no policy number
A148: LENIN PEREZ PEREZ | B148: Quote 246190349 | C148: National General | D148: Loss Hist Chargeback | E148: 4/30/2026 | F148: -1 | J148: YES | K148: OCT 25 | L148: Matched by name and quote number - this section carries no policy number
A149: JOSE ABREU | B149: Quote 242804983 | C149: National General | D149: Viol Hist Chargeback | E149: 4/9/2026 | F149: -9.02 | J149: YES | K149: JULY 26 | L149: Matched by name and quote number - this section carries no policy number
A150: MIRLOUDE PETIT FRERE | B150: Quote 244094116 | C150: National General | D150: Loss Hist Chargeback | E150: 4/17/2026 | F150: -1 | J150: YES | K150: data april | L150: Matched by name and quote number - this section carries no policy number
A151: KIMBERLY MUNIZ | B151: Quote 242985155 | C151: National General | D151: Viol Hist Chargeback | E151: 4/10/2026 | F151: -9.02 | J151: YES | K151: data april | L151: Matched by name and quote number - this section carries no policy number
A152: Adrian Rodriguez | B152: Quote 242611771 | C152: National General | D152: Loss Hist Chargeback | E152: 4/8/2026 | F152: -1 | J152: No | L152: Matched by name and quote number - this section carries no policy number
A153: Ailenys Arias Carvajal | B153: Quote 244530918 | C153: National General | D153: Loss Hist Chargeback | E153: 4/20/2026 | F153: -1 | J153: No | L153: Matched by name and quote number - this section carries no policy number
A154: Frank Sanchez | B154: Quote 244711258 | C154: National General | D154: Loss Hist Chargeback | E154: 4/21/2026 | F154: -1 | J154: No | L154: Matched by name and quote number - this section carries no policy number
A155: Fuenteseca Mendoza | B155: Quote 244645018 | C155: National General | D155: Viol Hist Chargeback | E155: 4/21/2026 | F155: -9.02 | J155: No | L155: Matched by name and quote number - this section carries no policy number
A156: Geovani Linares Bullock | B156: Quote 243273817 | C156: National General | D156: Loss Hist Chargeback | E156: 4/13/2026 | F156: -1 | J156: No | L156: Matched by name and quote number - this section carries no policy number
A157: Johnny Virreira | B157: Quote 242852157 | C157: National General | D157: Loss Hist Chargeback | E157: 4/9/2026 | F157: -1 | J157: No | L157: Matched by name and quote number - this section carries no policy number
A158: Jonathan Morales | B158: Quote 245802732 | C158: National General | D158: Loss Hist Chargeback | E158: 4/28/2026 | F158: -1 | J158: No | L158: Matched by name and quote number - this section carries no policy number
A159: Limonte Perez | B159: Quote 244645018 | C159: National General | D159: Viol Hist Chargeback | E159: 4/21/2026 | F159: -9.02 | J159: No | L159: Matched by name and quote number - this section carries no policy number
A160: Marilyn Selman | B160: Quote 245192879 | C160: National General | D160: Loss Hist Chargeback | E160: 4/24/2026 | F160: -1 | J160: No | L160: Matched by name and quote number - this section carries no policy number
A161: Raul Fuenteseca Mendoza | B161: Quote 244645018 | C161: National General | D161: Loss Hist Chargeback | E161: 4/21/2026 | F161: -1 | J161: No | L161: Matched by name and quote number - this section carries no policy number
A162: Zaylin Cruz Hernandez | B162: Quote 241773244 | C162: National General | D162: Loss Hist Chargeback | E162: 4/2/2026 | F162: -1 | J162: No | L162: Matched by name and quote number - this section carries no policy number
A163: All adjustments on the statements | F163: =SUM(F135:F162) -> -125.19
A164: OF WHICH COUNTED IN THE DORAL TOTALS | F164: =SUMIF(J135:J162,"YES",F135:F162) -> -43.42

Sheet Notes & Sources
A1: Notes, Sources & Methodology
A3: Source files
A4: June binder sheet | B4: Doral_Office_Binder_Book_June_Sheet.pdf - 63 policies (18 new business, 45 renewals), producer Jorge. This drives the Commission Summary tab.
A5: Full book of business | B5: Doral_Office_Binder_Book.xlsx - the whole Doral office book, 54 monthly sheets from Dec 2022 to Aug 2026, 2,706 policy rows and 1,383 distinct policy numbers. This drives the Book Activity by Carrier tab.
A6: Progressive | B6: DetailedStatement20260811_Progressive.xlsx - 188 transactions, agent 24258, month end 202606. Ties to the Summary tab of that file: $14,289.02.
A7: Infinity | B7: Kemper.pdf - Kemper Auto Monthly Producer Statement, agent 5517897. 27 transactions, ties to the FL Commission Total: $656.60.
A8: United Auto | B8: United_100208_June_statement.PDF - United Insurance Group, agent 001-1D-100208, premium period 06/01/26-06/30/26. 98 transactions netting $444.33, which ties to the statement current balance.
A9: Ocean Harbor | B9: Pearl_Holding_Statement.pdf - Pearl Holding Group, producer code 6883. 6 transactions, ties to Commission Due: $326.21.
A10: National General | B10: National_General_Commission_Statement_DB_June_2026.xlsx - Princeton code 9019644. 18 transactions, ties to Grand Total Commission: $871.27.
A11: AmWins | B11: Amwins_Comm_1.PDF - Amwins Specialty Auto of Florida, agent 246500. 9 rows, ties to the Agency Total: $72.34.
A12: GEICO | B12: Commission_Statement_35.pdf - GEICO, payee Universal Brokers LLC. 38 transactions, ties to the Payment Amount: $2,267.79.
A14: How commission is calculated
A15: Matching | B15: Every binder-book policy was matched to the carrier statements by POLICY NUMBER, not by name, so name spelling differences between the binder and the carriers do not affect the result.
A16: Rate used | B16: The rate is taken from the carrier statement itself - it is never assumed. Column K of the Transaction Detail tab is the commission the carrier printed; column L re-performs it as basis x rate and column M shows any difference.
A17: Progressive basis | B17: Gross premium on the Progressive detail line. Progressive shows a per-policy rate that varies: 8%, 9%, 10%, 12% and 14% all appear.
A18: Infinity basis | B18: Premium column on the Kemper statement. Kemper shows a flat 0.10 (10%) on every FL line.
A19: United Auto basis | B19: Transaction amount on the United statement, booked at 10% AS COLLECTED.
A20: United Auto 3% incentive | B20: United also pays a separate 3% PROMOTIONAL INCENTIVE line on most policies. By instruction this workbook books United at 10% only, so those incentive lines are EXCLUDED from every Doral total. They are still carried on the Transaction Detail tab exactly as United shows them (column K, shaded), and column O zeroes them so they never reach the Commission Summary. The amount excluded for Doral clients is $252.85 - if you later decide to book it, that is what it would add.
A21: United Auto as collected | B21: Most United policies are direct bill and pay COMM AS COLLECTED, meaning June commission is earned only on the premium United actually collected in June - not on the full term premium. That is why, for example, Luis A. Ortiz shows $163.60 commissionable against a $1,103.35 binder premium. The rest of that policy will earn commission on later monthly statements. The four United new-business policies (Gustave, Cordero, Vazquez, Howard) are shown on full premium.
A22: United Auto net | B22: United's statement nets to $444.33 for the whole agency because cancellations on non-Doral policies charge back more than $1,300. The Doral book on its own earned $902.53 at 10%, which is why its share of that statement reads over 100% on the Carrier Recap tab.
A23: United Auto signs | B23: United prints amounts owed TO the agency with a trailing minus and chargebacks as positives. Those signs are reversed in this workbook so that commission earned is positive and chargebacks are negative, which is why the sum here reads $444.33 rather than $444.33-.
A24: Ocean Harbor basis | B24: Premium only. The $35.00 policy fee that Pearl lists separately is NOT commissionable - e.g. Javier Forero: $1,153.00 x 11% = $126.83, with the $35.00 fee excluded. The binder premium of $1,188.00 is premium plus fee, which is why it is higher than the commissionable premium.
A25: National General basis | B25: Written premium on the Summary Details tab. National General shows a flat 10%.
A26: AmWins basis | B26: NET CASH (gross cash less fees), not written premium. AmWins shows 10% and applies it to net cash - e.g. Angely Gejo: $164.67 net cash x 10% = $16.47.
... A28: Multiple transactions | B28: Where a policy has more than one line in the month, all lines are netted and the Notes column on the summary lists them. United incentive lines repeat the same premium as their 10% line, so they are excluded from Commissionable Premium as well (column N of the detail tab) and the premium is never double counted.
A30: Items with no June commission
A31: Not on the June statement | B31: 6 Progressive renewals on the binder book do not appear anywhere in the June Progressive detail: Amarillys Gonzalez (970306264), Brudys Garcia (990100610), Yosvany Larralde (982064065), Ana G Castano (866496112), Manuel Martinez (990228513), Reysel Castillo (970570633). Verified by both policy number and name. Most likely the commission fell into the May or July statement period - worth following up with Progressive.
A32: No June activity | B32: 5 policies are 12-month contracts effective in late 2025 that carry no premium on the binder sheet and show no June 2026 activity on their carrier statement, so $0 is the correct answer for them this month, not a missing match: Levy Diaz Torres, Elizabeth Mirabal Hernandez, Ana Maria Acosta and James John Ciullo (all Infinity), plus Armando Caralos (National General, policy 2032597919).
A33: GEICO | B33: No client on the June binder sheet appears on the GEICO statement, but the wider Doral book does: Iris Lopez Sanchez (policy 6219586788) has two renewal-year lines, netting -$45.78. Those two are on the Book Activity by Carrier tab. The remaining 36 GEICO transactions belong to writing agents Alberto Manzor Jr and Amanda Montano and contribute $0 to the Doral totals.
A35: Book Activity by Carrier tab
A36: What it is | B36: Every transaction on the June carrier statements that belongs to a policy in the wider Doral book of business but is NOT on the June binder sheet: endorsements, cancellations, credit endorsements, uncollected premium and as-collected commission on policies written in earlier months. Grouped into a section per carrier, each with its own subtotal.
A37: How it was matched | B37: All 384 statement transactions were tested against all 1,383 distinct policy numbers in the full book. Matching is by policy number, allowing for the suffixes carriers append (National General adds a two-digit term, GEICO appends a second number after a dash, United pads with leading zeros). Every match was then cross-checked on surname between the statement insured and the book customer - all 171 matches agreed, and none had to be resolved by judgement.
A38: What it shows | B38: 103 transactions across all seven carriers, netting -$1,860.29 as the carriers printed it, or -$1,593.97 once United's 3% incentive lines are excluded under the 10% rule. It is negative because most of this activity is cancellations and chargebacks on business written in earlier months - real money already collected and now being clawed back, which the June binder sheet alone does not show.
A39: United treatment | B39: The same 10%-as-collected rule applies here. Incentive lines are listed and shaded but zeroed in the Commission Counted column.
A40: Not Doral business | B40: 213 of the 384 statement transactions matched no policy in the Doral book. Those belong to the agency's other offices and are excluded from every Doral figure in this workbook.
A41: Relationship to the summary | B41: The Commission Summary now carries this activity as its own section below the June binder rows, so the sheet foots to the real number. The June binder sheet total of $6,361.68 is still shown on its own line above it.
A43: Statement adjustments and fees
A44: What they are | B44: Chargebacks, fees and adjustments the carriers apply OUTSIDE the policy transaction listing, on separate sections of their statements. Four carriers have them: National General -$62.10 of loss-history and violation-history chargebacks, Kemper -$32.90 of UW report fees, Pearl -$16.72 of MVR costs, and United its 3% promotional incentive. Of these, -$43.42 reaches the Doral totals.
A45: United | B45: United books its 3% promotional incentive as an Adjustment - its statement footer reads "Adjustment Commission : 37 Commission: $6.89-", and those 37 lines are exactly the incentive lines. The Doral share is +$252.85 on June binder policies and -$266.32 on wider-book policies, netting -$13.47. All of it is excluded because this book is carried at 10% as collected, so it shows on the adjustments block at $0 counted. Every line is itemised on the Transaction Detail and Book Activity tabs.
A46: Why they are matched differently | B46: These sections carry no policy number - National General gives a quote number, Pearl abbreviates the name to a surname and initial, and Kemper names no insured at all. They are therefore matched by NAME, which is weaker than the policy-number matching used everywhere else in this workbook. Each row on the Book Activity tab shows how it was matched, and only the rows marked YES are counted.
A47: National General | B47: 8 quote numbers matched the Doral book, worth -$35.06. Violation-history rows share a quote number with a loss-history row, so where the quote is Doral every row on it is treated as Doral - that is how the two drivers on quote 242804983 are picked up.
A48: Kemper | B48: The -$32.90 is an agency-level UW report fee with no insured named, so none of it can be attributed to the Doral book. It is listed for completeness and counted as $0.
A49: Pearl | B49: JOHNSON, J is matched to Jahmar J Johnson, who appears on the same statement as a Doral cancellation, worth -$8.36. MARTINEZ, L could not be identified and is not counted.
A51: Controls performed
A52: Binder premium tie-out | B52: The Binder Premium column reproduces the binder sheet's own totals exactly: new business $29,109.40 ($28,891.00 base + $218.40 MVR/fees) and renewals $49,272.55, confirming all 63 rows were captured.
A53: Carrier tie-out | B53: Each statement was re-added from its individual transaction lines and agreed to the total the carrier printed: Progressive $14,289.02, Kemper/Infinity $656.60, United Auto $444.33, Ocean Harbor $326.21, National General $871.27, AmWins $72.34, GEICO $2,267.79.
A54: Cross-check on Ocean Harbor | B54: Pearl Holding's statement is a scanned image, so it was read by OCR. The reading is confirmed three ways: the six lines re-add to the printed Commission Due of $326.21, every line reproduces as premium x rate, and both Doral policy numbers and premiums agree with the binder sheet ($1,153 + $35 fee = the $1,188 on the binder; $1,141 + $35 = $1,176).
A55: Rate re-performance | B55: Column M of the Transaction Detail tab is the difference between the carrier-printed commission and basis x rate. It is $0.00 on every one of the 384 transactions except seven United Auto promotional-incentive lines, where United truncates the 3% to the cent instead of rounding it. Because the incentive is excluded from the Doral totals, every transaction that does reach those totals re-performs exactly, to the cent.
A56: Agency codes | B56: The six statements are issued to different agency codes and letterheads (Universal Brokers LLC, Creative Insurance Agency, producer code 6883, Princeton code 9019644). Every Doral policy number nevertheless matched its carrier statement exactly, so the codes are alternate identities for the same book rather than a mismatch.
A58: Reading the workbook
A59: Commission Summary | B59: Four blocks. New Business and Renewals are the June binder sheet, footing to $6,361.68. Below them, Other Doral Book Activity carries one row per wider-book policy with June statement activity (-$1,593.97), and Statement Adjustments & Fees lists every one of the 26 chargebacks and fees individually (-$43.42 counted). The bottom line, Total Doral June Commission, is $4,724.29.
A60: Adjustment rows | B60: In that block only, column N holds the amount as it appears on the statement and column O holds the part tied to a Doral client. Rows that could not be tied to a Doral client are shaded and carry $0 in column O, so they are visible without inflating the total. All 26 rows total -$111.72; the Doral part is -$43.42.
A61: Transaction Detail | B61: Every line from all seven statements. Column P flags whether the line belongs to a Doral binder-book client. Blue figures are taken straight from the carrier statement; black figures are calculated. Columns N and O are what actually feeds the Commission Summary - United incentive lines sit at zero there.
A62: Carrier Recap | B62: Per-carrier totals, what share of each carrier statement the June binder book represents, and the other book activity added alongside it to give a total Doral commission per carrier.
A63: Book Activity by Carrier | B63: A section per carrier listing the wider-book transactions described above, each with a subtotal, and a grand total at the foot.
